<RegistryBackup>
  <Registry>
    <RegistryHive>HKLM:\SOFTWARE\MICROSOFT\WINDOWS\CURRENTVERSION\INSTALLER\USERDATA\S-1-5-18\Products\008BB29E5CCB52C41820CAC2B3C7C7E1</RegistryHive>
    <RegistryDeleteParent>False</RegistryDeleteParent>
    <RegistryType>String</RegistryType>
    <RegistryName>RPRTAG</RegistryName>
    <RegistryValue>Backup</RegistryValue>
  </Registry>
  <Registry>
    <RegistryHive>HKLM:\SOFTWARE\MICROSOFT\WINDOWS\CURRENTVERSION\INSTALLER\USERDATA\S-1-5-18\PRODUCTS\008BB29E5CCB52C41820CAC2B3C7C7E1\FEATURES</RegistryHive>
    <RegistryDeleteParent>False</RegistryDeleteParent>
    <RegistryType>String</RegistryType>
    <RegistryName>AppleApplicationSupport</RegistryName>
    <RegistryValue>=JJ*5.q6R9m~e?-X$O^78(O]jRKex@feOx'VL=,is[I4rauh]8lcA^QNL)lu-yNtYXDhC@!{cKOQzal!uquNc2%0j9e3N7%g$goD)p4+qeEw!?-1$&amp;v3Z%RucEOhbFs[_=e8nRx9i4b-2L=c^&amp;)O]@)qQ(8.IWCpf.^B`ywEh(MJbFq+$wkREzcJiLEU^@P)3d9KnBfS&amp;'2L'&amp;a3C?D,j$m*I`Z&amp;49'acEdi}D7bDttz8PZ4uyAdI''bqBd)-(k9I'),IVA^Ip'n&amp;EBeQpVYa}f.Z0!0VtS](EGk^fQe+W7vVKJT4pU,hF0?&amp;Lj&amp;,m2bJ_%2D{KPhF8Nby4ir[qulPtobo3yeBBpz]V=2?]r?tV.LqxZ'E0pJ5qu,P*q9D.+XogBnACBq$E0w6ixdxynN=PzqCw0It(u6{y`k05AZJ~}.EX~k%w`Gq}JYrOJuGmz&amp;BY~a%0]Mwr`}zIy!LT8CC$AxHfAJB-NoL`cyP'LNB^P+_ow=]qiJ]+hMxMl$BMuA38PZJrVIaZdrEm49D+$M``8UX=_(k2{8Ir9IBcYR90te!I!_JGO0MI2QD$*k8Blf]tR`!@qQ?l!yDyxXDZuKGj7Ss9*%drjCE`p@)-oj*W*b%77tBP2MC1kDH$E1L}Q9ZceC5srsAS*AE*y'M1s[PS.Al({bD])k`wC$_oBEvbC5b'grA@Br{I?ni2HDZmzO,)0$EA20o3yn]4eoQk4ZBIA5C@$HBBGv5&amp;OW0mnEFKr0CBPdQs[4Y(O~}oBX4G12EzV(1qCX*+xXfvnuzO{{AC-F{.zX=U1JSS^oDxcXBf(%6@k6Gy2l5%k!gr~HDOmGtuQLo?WDS,.aoi,1DL.&amp;ru{XyB_32%@6x}HWB7JsS&amp;X=1eY*'vVZ=N,dFm,k=Xo7sGU)W^q6N^&amp;lAAJQhCx9B@q{cdwq*MkTD%iC![e7qNc%Rtc5-ppiCP`7XMjJQjA0Jwdg'K}7CTg]?!u(3T]urBrb9N=5D2c=%krmL5wZv'AxqlNgBEAo*)La_FBnO6F2@shEFw,]HH&amp;)3,^'IqMfvm0@?WJh$0ZhODm9LMI&amp;oL5h(_EU.Z&amp;lrLWvww%]AKTg8.dh_txiuY8V_&amp;-)=@0B=yae]UDW1_!dib_1V_MX=K0g&amp;w*}hinhyQ`II%Ah()Ycc2+$wkR!5sPG*i7c9a%EIdQdnl&amp;r['YdwCZh(~'R[9u3MzY)a(Itr!'u9(F}Mj~HTf6VZ,[iO+nR?=Wy3Kp=JM`'(Oa0}KF9A-CGuN6tLYr*=UE?I)xkF*tMNvIBz}r~0mJzj^`79)?H^tiY&amp;e6'Kj4ovdSh(uixf!u3MzYK]lh8UM5R=Bepx.p,GS2friVkY5xi=e37=gj6E0lD-RdaAUb_8=U}p(i?M)hD!=^z^(.a=1%O~ZWn(fd]+v@963L$B@kd0Txc)}(q7h4zo.0PA,[VyT`5@wqN$=hFGnJ=@K'OD^(n+98m4^_+q=PZD0(QXQ-kU9^sBZwEUP*y9n%!na&amp;D'A1?f''8^2Dh($po$+,$wkR*quRhHLtMA$wh09!{DP2WZZU[BV5WC3Y)bck{rQJI~@@9tFBb@Ms^P!f*Fh0}}E_7)PVx8S6vR(X!k1Q]zsM&amp;[Vuy=G(v%jl61+25E8UQIg3?9_Ij{B0_t8u=fa3]Pxzd8g1Q&amp;NR7ASS+3'GR~q6WFn9lk3wo9%Sk[AxqpwLq=Ts}8BZRGa0CQ%Sp@[8h(,o5Xp%lrLW=ojODA6y4=Qx!--*1=n!n&amp;dw*oHBIAW&amp;2+]_XEeBkpFTv'h8PE6(zoHnj)wtPLr]H)KcP?-qjORLj`=S^U`a123}NFL{ustz]{gc8Thq.5a-OEBs'in+cp`[%&amp;p-^gq]6?3a5Sl+5odFPTk-o})e0=fczIra'lSQ'f!F'X6?-CN-pj)`tXzrw%IjV&amp;OFh(k)_Do*$wkRDz_I4]=S2B-csC?@U?5V?qHuML?DJF9Y~E8cGsJ27&amp;wdH$S3y=dsZ.(}@PPk[IoF+UF?.?Wg,qf{}_ad8hO*BuTm.FWm[eR=`so!VtTyEW0aHC6SXMlDXpxXYCHc8JXj1F]Mn_LaIc&amp;*SjdF7DpJ[F3DE4&amp;lnbKQJD(OXsw1gBOQ?P$&amp;w{Rzr(`N!tS[]F`Bj4M]^x9*JYOLPsGPpF(m'GoOy-vf8&amp;)q@v-lPC,7hYYR7$P16Yc?R3P]hA&amp;H5_[)_D*i^?L(,PI[dCm$9*'6cmtcm1L5Bi@aID~Y=Yno~(_Fss=jC{bn0D815CubPG`t`RpiN4Y1BDNC6vAy`IT%-s%{Fv`$SB6!F2BA*VD'ioeRW,5S[E&amp;h1&amp;&amp;t%*pk@z'IPydwJBY@q9YEvx.3)[lh1G3j,DZrS`@RSbmK^eOuJJHjfF)AJ1x+A4$xklt}mQnF(Cj7-=%c!7NX^M%$!'if@DlkA'iSPJ_+bS!Js^V]aF75eP('cSbmv+Kw8LTMnCxmvo2uSaZ'deM9.+OjEBVMv`f&amp;!rV49'k[*J]T{EHe](ry~5V&amp;}sYXc'5]eEtftW5MkqY.pig'Gk[6ADy2f[5R{2l1PVBMMLIl4E0pgB,XmH4euW[2Q1qvnCNP`G_+miv!vDYQrhN=AF`1Cz1d8nAH&amp;GA'75$NuCD%F'+x=8A$[9Q-uJY3WEq%G-+f1[FrFUL%teYI5F8{n)A(U)[^-[i$PR=NXBdnn$Uj_2%vsG7S-dEn[FYdPG)6NIkJAY++Rnc$bB$Dq`yg[BegpIq@&amp;ElJ2Brd__Cu_Pma(S7(y60YwA,S6IS+_wxtUfAEGz~&amp;!EVbQeFkS`4wdW=JnK*1LF_`(z`yNedJA{iR?r8`YELZWBADf!KYG+9m8B{IoA+kk?Z0MAK16NkBcq`+KBALy5HNnpb4ktm~XjPf2BfsKGiB+c*Y1b79PS[P}EkD!A-4'*sAEqm(9}H%5D[s,{tNd5,XBl%fG7hBdBo%l87fO'0v(Zw[4Wq%!ER{VN-`N]7h{U}D1Ooe&amp;Cx(Ou@Q'`{hg4K-.e{TxBfbm'M}o`s^Yqx-4Wx@yDh%la!mRI-yZ5}{3AHHAB[wqFCE3E{^hb)]sjH6iBU4f{.Qo6A5[ZX,B&amp;4.XE0w0oKen`r%NtFq2fcNtDGi{316ie'YpQ{ICu{FOC2B[E2FX?[beuIZ,w0g+C?8Su4Aj~w8sHas3SaXRC)m$~),nx,zJbdgBkO~SC0Nb.7TXgf@BsrLg}`,vER5gc_EaNWgBoH[K]BE@DA1davEgb5yB=doNFDkJB$8+tCgV5bpujOL_A)EXFlQjenAxNTn_E.eYgBA^B$3oL.p)bC-6gh_,E+AnEuG$]a$!21's~B^^ih(RB@=RNC%wuK114TLb?'N$EDeNkRqhHQxl'hjYkeAvDG7tFni&amp;SB-1q@4,kNX'D4^AOK*^QkGIO4ZfB&amp;g@DkEC5EFj(B1HXJnml7*5D2_kIrL?$oVTKeZNJF~(Dtg*_i5LCJtN&amp;H`YyE0xBPx38eq0-,a2KSrFXcapChjy*xEf-0O3]^d!UGXRC$!5a&amp;vtx$bG`6esAsEAF,2B8Ck4EiQRt69sOh_,BZw7tYVswY'2p{B+3k!hEGDEX[gIkt=1rd,!+,aDD.~vye_RZy)]zDcx@$Kh(Pj.6q+lVnYgOg&amp;'!vu_@H{+j,a.-NMXSoMV2ogR?)r?wR}Cazg(1lGJC=g@FeI%e+1tY2iF$Z7SzGd@E=`nsynKhh3_3kR9G.d(Db(M%nFtY$qOh`=DiY6UB'&amp;`Tk2M(+okc9$LmjMTB6Ly!VSEh-u_fb$CXbI7CM&amp;g}?,sC4[24&amp;kG6dc0B'S2h-Bk(o@p6^))soq,B?9ZHYt{Bccw41X-q30ED&amp;O$FF-qD=aS,lR8P}A`FYYrc0NE~-Foke}AGZ$eCm,ChU^gYBax}Cz9?w=oFmf!}yF1oJFlz5nx4+bNEjr_.IW[b[z_%_4Z~ivXBBLtSEU.77V1HXhjgd+AC1E6m-zYut[^d5WN0J]7C%!8uLfc&amp;^AX2kzCciiiFuj{[faoMOD0^y+%dmvPC`_=SnnC78FktbJ%QZIAD%}{Yu*E.ImI=v%_tZY&amp;FMom8^?6x9lX8`8eqO7eFKt7'.l!O%PT^+N_t@Z6EYY(,kgl'HcEBUK,2%v}B+!Y)X+p3]?0i.p^Lp=BCA-2lHP=syb+)M6F@p0HFHtKxaOiOhN3E)r5`EtoAq%t~[5EDcwf4okwAH5GBDG()J&amp;aruKC&amp;awrHWgBB!sgU+soxHS'R4fH.oa5D9`[gxDyR?RWa{eie&amp;PKEg~C8Ee_^dxOGWeh+MsoB58J6$DM{C]21d+_JPq*E&amp;0Bdip7jkL]p9EdyM@=E+=PZs=ppri]n1d5zMV^FF1fr!^wI_AAV)qc]ORXBMCRSlFG^6{0}Ij=oDScF=NF=?07s[G.2^)K]*dLCetlO6w)L8*[gwNKz-_dCuzEYu~I1nf._^+J^}5{AJBjkQp.^K_JR0+H358QE02lU_7OT$HYKAK(WqYyE7a5E_~bq[XUqWx'qWF@B}ouy!vG=`Eo4HfI&amp;{YKC4OcFmE2!HnFs3m+9n1=D~ABTWb8uYPY%8BIXDPeEJ]y!lrf)WKM{Js-]&amp;xwBUpV45j]g[qKjUh33q4dCA(4H^wu=y?[Q^e%Xe%qDYxqoTkNC!+8Gt._IMC)EpN@fVwuf@gD!wAOwZCfE_{aBFfid'X)GI%Bb4.'C@{UEW]nIX@wj_Ac64~DCKvyKVS.xi8U)'9M`661FyaRg!GTPx%a88xh.O4mAFopIq@I2QXBRb&amp;QStl9F^(Fh2g}O%ki$r[Z%&amp;M}BeYQ?''NUIQe[5vAt6mKEUfvWGp8Q'hQ,kNJDv(GCdU%b[`{T$2!2_Tije1IB(_.Qv]6{kUL478x*0v~BcF{&amp;9LrlLZIK+.G6)moDn8z2S-yXgTE29nLvHB'Dn5uk^6Xj!9thp,txH&amp;XF$Vu%.=!Ge+A~s.P+EO3B`KNj4}zTg77Db=pvEwiDz6}b7OkoX5ujFz$zhy!Fa@vk70SjYQ-H81BKz4{AR+JGM!j=-vtA)uh{WP2CaZ33$ilaytgC_.k,Dv*C`4ax@8brC.N}(QDJNr`B.gzw$+~@*Q5BVepkEIN?pzPIOVsNl^&amp;id)pbr-u?^)uDZWH.z'NJ'Fb2@XFAw5L4*.QRnmStO8oH]lq?d4NJc}.wnv0XFPo%'?T@rqsnz+=0@u5JFZkYqNbCYiz^&amp;NLzy2{y&amp;{gs}EiDPgs$6l6uLEQ9arT]26x8(Ufr@AMB?LoNj{%3`R_D5.G4,nk&amp;p@6}chYGPbpE[(sHq99SBi6]1C.q53Q9D8h}E5)VrdspNPZj1WtBO'pP0)r'8th(1E47FvWDxLy)p,w`=mEs{3m6BLG@SX+_F1.).dF{-RD-,2}B0IC4q!~Zj,wAIFxF%+TE%tzC@ISQ=.M2se@F%1}EM.B&amp;,KVMwv3^?Nw]g&amp;KDkxOLU&amp;[n8fWD_HhHO'mDAAwEE(}*iH^2(seE`hiB?('=kTYJ'G'lj6R`bs`B}]28(-@ZE?MQQBuvW%WB28?pf&amp;RTau{LD=`y?^{?z$aiKaDHSI}r.'^zRS6BCVuAKi2deHHp+J?zkMb?efmz]Kv^kzVk?P&amp;RI^FAGhyo?gg),IWJ4h8^=35AwQBNIhGA~c9.g?Le6%Z=9z}'W?g`)EDVg4'-KZpDZg7ptUZy`-@.fzbBKU]=urj%ncu[V4D-F055[`*E)d^.H,rC0p?UecM,BoAF29Uo$K=gl5N*3ifqtid86OtQz%x%gXN1Sqd],nPB5@gRqBZvuQ`Kw='D%uXEuOqrPtu874=7=H&amp;^8+yE*2TwmCe]q[EFjP&amp;2'V[Dc]S`9xT&amp;}f7U$FX'y3_@YaY6K'0j10FClieZawV9JZlCt~x*kC(9XXH3Ssm8ut6ZvZHnL3ySbJ!o8leAhVSMi5pxFw@3h6RpS?!BzTqP2PV'b@_o.7RjN(5C]d(b-GE!M!ODvnL[nR=EZDy[`7Y997z2YJAxKHY8W%t'%9@WeQ9R6A_w1jj?yQId$Wt^U[m')zE%Nf`AiL=kD0^@^MS$)-Vu?y%9c`%%I*l&amp;VDKAX0AwdE79q%PNkqY_Iet9k,(=cw_9`U]k$q3[1BgatDC5PxFDwQ0I3HNUq@i_o_?xrl4C[gmkCVae=El9H)T_ec6Dm_'V*m!J`[gkeqTtObIDj!9*_zg`.!-W-Yy8+u=E]gFKd`[rHi]&amp;?4Kd5'3B&amp;a7]^t_R9PQu^5DoXAKE.&amp;m3.1,NxX$fbwgW4nkDsn584]H~g96dH1sQ)bkF$[YH4K2Eq]xp4oa=LwvEdEwN=8q5hQT,4q-Qq!ZB[*LG6mzC0YCc!EXC&amp;XtDLzz''Ml54NyoX(HMcmcEC8I?lPHA91YW*&amp;ENdGoAr)a$&amp;G,O]-Vztr)}6aD=6.V$2IdV?I(MwVdv`8dD~muz5FRs{w.pVOm~&amp;I[90yiBFnM@mA3H?vHly~`?a!f^kR?g1GWG!t)LnM!=dAJ,A195YAihK!O(H$eA]cN_8og}iLP+%tSY9lJEyU+gHGwlbc4@?p-rU4}DI0-cZE5R-zk_s*`AyR7EI6eo0eZCYwK1o%I%wBL@Oe'RFtmJrF@+_BjCh*V96JJtvbLb?7BCTxu^4ovCwO^b5P!m1obn^W&amp;ps@u=E5dIcf[rOd^}h2?*o{Y?qqiA1w{ZDX-3lUVK+2WCdB]sx%IG@C`5(p[o{C}85)cLKydI`^frEI'kxRQ?(wuc!*rZ7OoYE*IM~YrEkrN{PeOQcp}g-Mx,+9DBc~SI%n${[rbab=v$WC9B'Ffk4E5dib0rcyyHsk4F,og-ftTG`%9rYaI?'`X9{(x-Ssl1&amp;&amp;SsNXF9Tbg=!!rT^a^P.5*?5PJ{Jp2?qq0Stm=FVOuF7u*Gl]~A9'[73pH73xgHR,!z`]%9DD{nEoRcT^8j4,yB49T?1kK3-v.u~h[?N+SH75X9iLgMlfwsZ-ru&amp;oVIve%F(!Q7LU(Z!l~M]mC~bvj=*P`Pc`6908kVDCJmZEjE2{Pw7,j84{PEQ8a7KO?ADM{!ti{-HUPu$F.I'cEFXtU&amp;2i}ls$wS(GE9i]g8MJNnVgM?RxQzBm55bK`BPx?kE?kN7GSB8O]caxuD2_(jG{UmGA,0XFUjg=tC*V[2zJPh2(PBRU'aze&amp;CHIj0gMw0DQy9m7^2rrP9Z0Jn]S'Vf9dLcmy]3Ne9[U(ouqTlF$P4euAFnm*?E[F=W&amp;^u@N}7]*3qvm(BWO%~iWsnUVj!PTZ+qjwD&amp;yP0jAiG5yOZIPo{dc7ELBfbhbqX-2f.hWwkBvtDny{,f{bxtbxC9=NRyP*@vZbFf~%wC0(KmLb)NFn9H]$N?mJ*KNQF]Ja^Q+Y@wA+Lts{cYmE?+_u$6Nv?},CKq(dn&amp;{L,HCEquDJA^kSScdyHt9t_fgoaIny?[]MoKOWXM=BqS=9^CL`=l9V'W!]l=EA)4]_*=v.Cc+ggG_~^CWDDshDjN-[EYD3Q?41eoG+kOb_fb&amp;BB5)y_SQ@*nS+dXsH,Ty@D{j6H4QPke$`N[HjS^(DB2Y~wWm8(vjHYo9k~TMGC)Q6ym)v%s-1gsFR6s(_C)h2V1zy3&amp;3ianZz8-H`F('@OtHV]lD?*9m=Jn-YD?.?^2YdW^Q[Zw.7Pj1WF*UA8{fYK1&amp;*Ds(ieNNUE9%$12r^.6zi]Gr-?82)CvZZOGA{B6[H6SU&amp;D5.(CiC.pyt$F@Ei,pqETQpMBffrKhiZycto1c+l+rz5D@O.Pmz2Gco`k,Aekl.PBDz)[!yR@YQUT?Js~IoyB4oo}dgF.@A(E&amp;3HqW4GBPZfYV{i=ZB+TZltMI{UF?fSPa}rs]H.CaX`Di7hEXqWfWW(*fzyzgLD?Nw%Fdi)8bq_'OP3nx~rX8=5FmMfY4@c@n'C7'%6GXBKFmuUYSO@w[_PAr_vI80SB=N7Muq1[sK_JCK4($RjC.5^%N5F(_&amp;-o8h2JPxUC,5CncOXj1VB`yDXIwBABnUnALq.Ks9aP5pS%L?lFo7]bM9lv}h9?Za)qI&amp;6BpTP6A%tvmrxPvGapAj1FgYHERnI+Q%VnmKtKEMDBWb7fVRxk}fTq%_1G2pjADx@4mbNw?'xBDZaEyc2ChqT.@Rj0KfJd[c8!lSDE~SoFq2D[zr?2L!1o%39BI&amp;j&amp;7E=LZzE&amp;n=iL7c^CBN^$f~!~cfou(WlY=)XEe,RG%i91^LKOXRX-FpWFDOwkzAJpbcE+Mb!sY,DDJI]73$T&amp;]VUg2--f')KD,,n1Xv7{t]XTcks_fasD5$Zz,r}'?Nd]wr2NxT!E[o`v'.qb_npJ6$hHYR%D5PIj']jVmp`gBfx]M6gFl%xCXGfp&amp;Xuhxkr9nF^DWT`yk?na1B3)%LF,}f%=1BsvAu6_AmEKJ=*YswJEJR_0yj?joxU,e$^7glA9kG,WM!a.@w9Z~3gGaa@CUYT}.=yN{31~pV4hO*vAQWGpcHn8U+&amp;eH10[=&amp;WC,0+op~un(F+yX*x~s!@9TtjYSk8LaZrVIuM3,N&amp;DQJ[uTftDR)c-2G%paYYC@l~6d-Igd?&amp;aWKIzsxJC{1?mw$v5rQ_N%@5pfo$A9})=ALX,kj&amp;gZVRktEMBZNI1uS+%.Ai?2MqWucjA(owYxF%74u={An%vcWrD0w@pMGX`iTHD(sg{=549)_T{Lf20!uO^]c$5g[YF^)Y'wp0bYfl*d!M2sXV=wc?aBhk71,H$-]zd!40BSP6K'Ola[qTH0F6z^-zBX8PRURb$hs^r{99syN1B`IIexoU+i.vUnm[`)C=B+YK!xkg@&amp;m[_hzG@S{nB~`[X0.%vQ$rlQ+{UcB'Cr+qlZ=e=3qt&amp;9`c(FFoD8ATtjU$@AtqtCbgsQZoFN=Y7hm(zB4FU,uxfXTdC68iH1JCwq]728v4H]LA9bcBy,$]Do-xt]MriB*bE^0h}@BME4A9R.Nr=1I]=+MJm2~r)AD(lQsov-a9DJ5-nkWR@@!*Y-Fg?hBw?zN.`bE]R$']f1I,ec`hFH^,3!n*L4X2k&amp;}-aFL]F3ylt'~m-1-Ye1}Dk?MBDtQADf4I=G]ttYR*r@c2Ab*^Av~3[zE5SRUHO7q^C3Kj-NXL(PW`f2?$4}c6AF'6iIl=}[UAqnFh9K5YB8v{^+~E4K[67Xj5YXbb=Zr9!WaZ5e`!u][ni!,vBSHIbnj)G8[0R9!ro!Z~@a^[hfoY&amp;3GW`7tDZBvlC~.6f,'sKjZoaJ@1`rXu9j3foB~ffH961FX+Nl!&amp;DqDAcS!qm*SMD1[8XlE7F+1ewa]),}YO1Lx4EgXCCOSq%DV%SNQc]]HwR}qp9i%Rf?u@9H&amp;7ntKKv=iHBNy`_5G7DD^wlN~`xrqnDE9zszmu0pYVwg$Sb`0mEcDnCdUq31Rc^NrYk_xZ8H_zs4F2L]*[aeKgqNLGF!RCwJ)i%1s=W-d.(H_9Fvurw9,O10UB`i+FB_xpC-EsYU9o%SrhxB,c(?n8EF3,1WTp1mp}W.'$FH$2C49B%Et_n.`7bxDlhP*dFVwhloJf^y9La9LVQVKJC%P04'L?gKXA&amp;cLF1b%2FK5kLqO}1Pi%C52$5ypKCm84zUkhL4]E{U_y(B$}E2?ESZ-Y`DT-qjs68.k+D,D)Naob0y0&amp;z{ieCBx[F3_eVM'h'!s2)Pv$F^~!B=L*sum&amp;A,hQCN*JVLb,CRv-9iSHUI$%WBbO6aJeD5GY5J*+0_45S`YFyKx6D0@LZN?dRNMo.CnIyBfBD?&amp;Q7LdD`$l@$XVQ1fTuD&amp;+GKus7{@C'*(6&amp;o_b~Evhjj*N2A&amp;XIlK(zZ{$BEBS8OSJhG+gztpYbf^7EF.JdQfc+H9{-fo_r,RldBx2.B[nmKM(pViLOp[sZB&amp;M^,H(vz16L`,uE^t!?C!J(DfFPLpht=7!o50EaBV+5r%-!??DD0Lpi@Y%5D^e36(X`D-lQXMqJs+}1CX@sF[GGtCNz(7bNEhFpAT6cKfvAYz,O'O)lWjPJC%wzFwlYq6`{`TOgbga]FN7&amp;MKQYdJ,,B9GkWcCCFuW{TnHL$S^fK})ddG(9D?5[{hv5^w1`Hsv+@g[dCpQ&amp;&amp;[_GEcqJTLdRhSNVD@@!-=so[-)^9WzUR]L2CkwF=68$rNfYNV[RoKCvDUP[AhD9vh4=Z5VrMCaRF`IZ[&amp;C?`.h?4Deok4{)ELt7ODZN2OCXnS'xV^JbFFSdvLS!7dy&amp;'Fgm'T.DC-BfOfJnQT2ixzo]2QEGDr4}-N)xGl%`9HBaeGk^BdATnJI1g[&amp;9pRJ'H2*]Bqyu&amp;10n$(FhyW,FPJ?UFb)s)(%5`&amp;1bWFjia4IcDh0DPprgu^EB_LLVZ9JFD%I.zNCroIGDP'^q?oV+FzOB*z-Cs&amp;png*HL~JD+CuCtmSK`=jO(Lh7*l1)-B@KM,[VBp6hP%PE6~QVrDBCf})U&amp;*OR',SOENT%OCeT,XGhL'{U4qn^FuC3nFa+m2azG%,t3M]^0T`{(FZ`H60FCOo@(_qdWqe(5CL7+dI3.S11Omc$chH^NCSP)*iJZx[rX4h!I[BgnCYG2]z8qi4DU-ha1fu.WD`jNEGK$3WhOc!&amp;6rh+CDzFMwmdERhK%1*W+4$N4F.6dx0RSSpih'3+?=c!NE&amp;{q=1{Ht^h3Z[}yM'ssEZb~=_SZmwfg8b8`EFRYC88zxx4m^'2RS.~eU61gA+IgPFZn~`.qS0Ap&amp;@VJDR)-$_WZ?CDZdiSrjxqkDIkEzUIHv.H$7y^trPn4Byz=^+Wi4aV2k?Ld]1bRBD&amp;5W[n)*9lP'&amp;_VZ4rNFsklDuJP00)[eEyj0'_EEN@^x9-cEre,^L3ag4[CF?aB%,T+?HvEd_ks!lNrAE3b,oip}FNH.'`%&amp;^MOD&amp;?8DZYRgE$kWnKgBi99E!}M{1Vx`BP~d-WOs@yHE1TqTN`lDU-q4qBK8}X[ClM)y$-f@c5q?yB-5-K-EUJbJBNGH40b+iVAw'b&amp;D`QEyl%nATLeNUo(G&amp;3AC?ysWE$u30%DUbc1wltuB_XAsQOr~jI30heK5KNuB0hbiV=P{VQUxW-QYDW6Dp!ii80KiT=bSQoEe7[2C?VUICI-yZ?7fo@?d@inFw)*`FIYUF.W%1cF+vy%F$UiuR2s^6y.Z]fBKxjcCtAwUO@kw?TYL2K@uzX6Ec6L`@^QEHH8a_nf-A6AFe2XSHNJh9B?zYpBwrqLBhw,hE2ty)*k&amp;Zb3sb6XDXSL?Yp7q0j-jG-t+2_jDsU.8bo9S[K+nevp^V^bF*dTeawfA8ZQHn,hBPTDDn9v69vcgC,VGG~iL)YmBH']&amp;*m4b'*Yng@6iKwtA,+0udQ^I]Esz*`Csi'7BzUmbhxufTGmi$Pvm]-[BT}8JgYO]aE-^,]vML@_DsBP`O,4Xq&amp;@'2]z053(C*p5I@@W[a($`$skU,!MDj37Ix&amp;P1T.E5A5enI)qA}1H'=nSrn)E=x*9^U1hAdd`i3_sh6`nx%j!?ndNEJX?F'7N9YjW`u&amp;MlmJ%B7cTwvF3Cw+9D-Tx.?geF,V`?2`735s2?k^&amp;0R8yC*7DpiyTqU_2!`oqn&amp;~jF[~~41E~csKn&amp;Tz0j*I%BcK)vEZI-[AJro&amp;&amp;yjzyAbHFU9I6-E9g$.?p'=6]Czk]5XIdh6@uyg}x1LLlF!vr&amp;16EgMp0Z%^^6Qg[B&amp;oAF`L*x0Y~0nXI^X^kA!&amp;_l^Q76Bj8uNi7d`-gF@]F[3(wl?y[O`sI~gAyDF.Vi6?v4Im5IER8Z0AjD5AsH&amp;FaiGSU?=smCY~oA*S3npe=OpsJ`@W5x)jRBbH}L`+H-vAq{EXIBN97B{ROEL&amp;0cu7)DdE!v5ZUDWHcjdU{jyd%Yj^[OFG0E85^3=a,b.,b}*l.b{5SC1%IPx[qz?QZ292{hFfuEJYVOj5AFUoHKB?+T=j(CI(nQ+1PKnrb-f&amp;$?NhCEoUEhCWhTrAkrT[bK6[UD}BI8VRIDg4~akxc=8_eDs1c1cZL+SY]rw-32t%GF9&amp;BldxplUiVlM+Jn^6{Au51_Im253@*lJu.aU_tADZ~82!mo_0bKqm3p*8jBH,b6c+4.)_DxG=Yw6&amp;.Bkf1V^(oa4UEEDoH5U@.CW7BI'Nl&amp;v5lbQ*zChShB06OospmQ.H$P~`_zgN7FJHikTCw&amp;H'KWo.iRtR=EBxOuNIGX'tL6)XQ'7{HD]CJ~Rc3uI`uRZv*FbmfB?!@+CCS~y5(6!T3@iZ^Fb6M,L0=x4^Yq+Y?c-b1F87[THMStZ[8dS0N{^yWFw8aI.5rv-_@cpYFY'*1EQS'+Ie.)}@9h+$czaBTB(!A7uV9Qw)q+q{U2$hqBz22*U0sv}ls2*zg!)I2CPLz-03q5b$]wzNU4b93FcgC?J&amp;oLA[.Q9bvq5KEC0gzwVk0[]yJI8c^uJcMDC`3~[29i}]zDh=z0NqcFUg4lX2)u[tH21!?!G=GCDyn4Ykm_uW3sCrt*ZV&amp;CJ+7](Tec1zeyh.H0BZNCv+t^VusvhzSQQ$@Izq?E92l~inVD'Siz^^aE+3HC)7l?7DC9uS~ZtPb]&amp;g!Eo*dEBH4$cI7%k0`IAM&amp;B!+IsEYdJm)2*V2[aBwGC?(xMU0sh`Za3MBL_E!KBOAP%3{J6)t5UYDz=uCFDL[bN^bw=BhMD+Qi]'ABD1u]-9,rg6u[uXe$]6^7BO]t(?GkBfJgpg`Q0-)rBaDeV4E-N1^Zueqs&amp;ad@FO8qaLwX5q3EoSutmT`-Bsfjk@$Rvh&amp;6.p}+S]3hAg{P9-8sa=Ux@.?]GB)$EoLKm@%.whf&amp;R=Yf160)FJbZ5STH0]'Uwd4_GqltD.[76'Oi{[+A2JhQetMGEzP[7HqM7~]nt0HUzXEfDZha^E,-rQ&amp;MEda&amp;ZI[wALIriwEb_WpQE2}'HqXmB,eryD}8kkGL[_(!^&amp;{xAP?e8mwQd$M*yk8LJSz'C+Mq&amp;eozoL]e!A8f,4*5Bd$%KN}iw'?UStg`y*DAFi%ZnMMk6=.Ebpp0.=vHBKW6srOaQbWV&amp;3AXfVR}C?fmgPkV5,[^FOBO798mBY~Y]MIfklxnXB$.ua+dD`A_7u0Co]2F`y8pOK,KCtv}sLV&amp;Nx9FNslggZ0NDPlOEZ}vFxnl*_v'$N`6EVw^V,Gu4*@.9qfU0b13CLwaARCKVrB5HR%r^_a-ER~bcf?V@&amp;`i.~!m,`aiE%[Pwean9mDfmRe)7U~8F(ZO~Cvk9,[r[D?sbWD!D&amp;W{lIc)z6kZ1.82?MtTC=Z+kEkqN{%xu6F4V1CSE3QNFSG%^-?$IfJ&amp;N98JC]B0yj{!b1n.@b-]D!x-DG]Z7JRsE`U1vQmW^jLTBmVE_a*w^~@cuo0F55c3CjFSmOSZibgQA'pH=uONFlO`8CaK5}V*Rw_va%5WF00{Oi[t]np0B=dx`]5OF=HW[i}!+QGHZ.`k4~_IC+f`_XY{R(l_7LT374pbFwV4ct.4VXD9&amp;dL'=('PF?=@~HgtAAYM*_*d-.CbF_g+p_,aM?m4wW6-BSA-E=ZS[,F'z^`JgS3gqjW8FO`HhabLk4?m+pQT4'M_EyCLwfJgK+gZV4s5m1FqA1DkzJ(tPlotM!44MLX7FMy=G,7Y3_aAq[rH'[aJFs?cqH)@~*`~jIj.U)QwBo85g@4,WVSEE`eH.hs-B*U?h,1dz1DY~6AfY.NaCq?.s^}g8zWMf@c8]JV1BJPWepdHUl.a$.b2mov'FW8QpEfV7?'[fOwHsZ%lAz14AAqsV&amp;H-qB-a.6JtERnMu1$&amp;`~i@QEPl,d6lE+%G~=)mmp23Kv*F@2jmB`@Mz)X~cgnZ@eHd!j3ICPfkyhMT5_TZHZ.Q+1NlF!l_OXE_d6L^3&amp;HB=E[FDL1Y=Y4m+!fT9(+U1qx,BucOq2=B,}Y^kpE)kzMpAbPDfeudl2Ets=9zFO~AFK$2waIJWv8jnV[=GjZIBTERr''{Un={0*oL^uJNCC!3l4F{^D!9[bN'+6naD,{cx[S`^(Bj_(`7fNIUEN)OnL3-I4rFNucVz)pGCRfClH3{2]fQLkp=qI-NEskkdsW!z&amp;YdX*0m9nPhAMIqok'ObEk%$rE&amp;nAWtBmvQ&amp;!9{7F_!G`jLI{O3FmxJ`9M{=pPKEWdC~F_wE?QfMUkzY1Xgx,z-@_V,ERrL7CLnH[e)e*N+c=*RCbCn6TT(LKY*{BKyhBnKFm4iyIv`dlBi^P_iE78GF6(P8QNJEtiTemZPLLvwC~zVbDo[ih-Hr2AV'C8PEzv_s=9S].&amp;.Ss}MCUIxE52Gq%fAAr[m7]VLTggeFn[.U[FPj}]{PC%?[aTRD*^!(DbwuVrQKWp3Y{9~A]a5Bj]4kFD.Kvqyz=*zBj9w]VyysDf+)W+ojmCkE3l)P?EYt2^aya+D[yChB1`w}4oPoKU&amp;E]U5BK?'DDgo[R{]v'9.Mec02u!vB4uNK(aXzvizI`pBV(7^F9&amp;,'?`D'jDR8pciprE!DOpOW^_{^.!v2tJSE~96B}yjc^WFXS'{kpNzg{[tB%5tP7wr30=fi.=!eZi6F4UG=v7s2dF1HGw5S.HoF+AOv3[s69a0Xp8a1EHeB5B@_9k1MQcqSQ4F*Fa_DHBJed6ao2E+8A{'3ij}Bxm_xe@cO,XSUKBVPw=hBvXw0jI)zZHd*GI)s4R[DKu+`kZC}wXVE3DZoqaQB{{pH'hZ`9u9@l,Qy@6RE%50ZH^8el_*L3@r@W+bFI6z[i81y{`gd%&amp;zTP',B49$&amp;CqM*SL5.Ue-{~1'BBe1UH0,RsLc,+{C}wLvE~uUSXV6A*dd$pfoXJKTFEliH3XaHCxXAta6BoGRCb.l)Xm}Q^Tooiyu7,,JF_FWQ7501i1?syqc{N6_Cb!j,2E%tXB~?iflBZD}D580JFXDJNA]B^lTkrq&amp;C$PGYHx[OKzCLRaT3SEoAU6C~aOY%[lG[bNfXJuOEd0D@twLc@!G@@la@{%iAS2`f`69XuvNyh7bSWb3B~&amp;XcL`4URC+CQ74*(-QC$Ghx4CC_u4212b^V67PCX-G!s(diR5mGbf3~B}TC+k1r)WCEUUy@_TFPM9TF^3Z)FEKoVujmFfG.pZVF51'!G3{gk9DQK]][K=8BV!4x$YQuMMq`Rf4.@=!E~d29`35owz~c'w4my,TDPAWRj.cH+ch~U*Z-7RgC}QM@0r]Vb*-qgJl%cttAznM]-P_&amp;I(&amp;4PdUn@QRCXU'Dd,*=$`4dm2v]tX1E`!&amp;Sj-d^G9f^zK[&amp;mo`E_gGMq5gL9O2kPy[AuisC0BU%cp3vtdFC)9!pLfJD(ycc6qzNdi'..rs.0eWC]UECz~zf4FM.JmL2QfDFMik_ri1eZ6tjU9$4O.$EWy*iRypKTu-!*Y9{T@AF*$~h=f{8NQ4'Qr)^j=JB**Z'%t)V--uU?]8?Z=7CAKb(P}-L'6i25szs80uAhhiN4qlyymVH)*2!DNZDaExHJDx$v'hk)bVga@2FyL!Ua)gu[yfF_7?S9?iFQWD~I+[KnCCK1Hy`OoqDwSbkDS$Bx*n)UQAKqy@F.sdu+tf,e,3rqp'I'+ZD7NSApu5*yJ`hM5-YjQfC5nVe8BB$-$BA%g1yJ'jE,*+UaAqSpO!b)}W*h9PFltIx]r9d_[RZ(!9O]hZC8yL}7552x&amp;3GC~Bi=ZGE_zKWpU~tO.ux?qS9C!NFUgMcEMsD[sMi5l8fHFEEA)yn'5Kru6WC3C1_xVqF9Wp5b-,O?XuR&amp;H5o='TB]4e*%xNqSN9{S.[DLuMF0(hM$H,NU'WRO2LX-V~AUcxjekZn=V07Y@VaHufAFp(qNEL)oYd5qF_J}&amp;.EC4@9G)@W_q_V{%fMm1[C-dA^[fyMymii@1%oi?eB9*u*?_8p'{%l$KGa6SGCra@pMvtpCLvE{K'P*z'DLv}Yc`&amp;}2A7p`QEQBH'DB7_+FT6N=KJW}$ThZvQDPoUa_.kxUy5!j+`ob~UD[X7Qyi$!@^'H9$B($-HCT18WpVbv{FRs&amp;NDNgmhENRO&amp;X,ZGUhQIJ2r^Me%FC69DY(jW?x4f+a.}t]TBoSG`D`,'+qq.Mxyr}%LDZx.Bk6*mw=h`yLbfR2uA9FARXH{QD0w.?YeXXUWD[WV=AoL9@lz2tA=B-~`F+D,'+v8c%uQMMGMT!*CDuvfb9X}GK+is~d68HRtA2zc_5fkRZpm{LjSHRQAFPfOUB13[Oatp&amp;^c)vJyBxlu-8mTy26@.&amp;gteyx9B9wN$K~sP7(hURsy1cp2BgD%UOeGbGc8-C*zch%oEjl'rkjKa1q=N0'l-H,-BPSlB[BL'c,o-Ie.U-3HFs%?oSQ9R(rwd21`@@F5DXRigwBg-.7+1d+Nhui-F7w6T1Y)4ND$!TVXF*`dEGV~De2KBv*0E%vy-80TD2vua0fl*0gqI4[.L(*~D$crkcGn5dILV5vVD84,DmybA1u4Nt8ABL4Y%K],BlQRg-Hv5)qW^tt-Y=HnFDq!]Q5vTyAnlJ$kfRxjBYKb9qSIfg5+sALmOARGF52gtktzik2Q=u0qxOlED6Akswp5KNG1zq94.axlD-4R^'V4HovIYo(){lEYCf=oc8!lQ)ppVNU_HUlZB8CwIFz-PsvQaJZs$7(kBK{0MQS-=(uSXB].AAMACZr461~hrsK+_Cn04(S[BL_y!dY_`RDrX6kEfln5CqpT$Oy*rjjDHxcHFoy4CfG~q5x7Z+{tB7?hmIFJFR8(cz{mIfw]jV,OFSNbBoccFT7ah&amp;skmSX^M}iLFpY~c.J%0L2nH'3niaE1E^ql}8!I,Y.mL+aN0+1]DRT)a@_L.lv$NH5aTtbsCKXZ%k9MuCnJ~4Otf17vCPQba=-Yg$.)~iI^S,cBB4IJ{m2bE!uhgRSv$%%+C[y$t,w=n,S@9LF8Jd8[B&amp;*9P2EUx!zS5otj`XIxBo7(LCD+}gh{.X?4zWSCB9&amp;dB%mG,8JKMAiootQNF(0c`n5f[YGHRN-UyQ@xCjfotU.YeV9fR)+ru]8uA21=fzj0hxxq1e(2qx6(D^A*_(9ZG4sbxkTs!ytLDK$KU^9aPyEc{L4_l&amp;'LBKy'er@.BwPo)7DN%J+lDVsA6hkM*x+OKtz)L*xjC09+Cg1I3T[^*FY'hNN`El`m,+qy[HTWoeP*{'BqCgPhn[HYC3xcCgy?c$jsBzSw)p].dm+KgzO71Y`-E3L~$OoI55umcAAxn3deE&amp;d'1R0h`Bqr{as!J1rfEfv`hAItJ_H!1r0$C}`_F{HdYf%iVO'iu8NJtXMWCB2+8^OL0o0Uy4VaXpzyDj~p]^YQVsd*$g+]cHR4C@'*{.J'x8Ac+S%Relj8CH=4*K,yM(.z)ewU.gK)B%+[qB5sH9.1MLDO,(B0B*EG[g{hh~6)Qp$W%p3.FyT~vVw6TsZ9$1[xm_XGD&amp;o}Bn9=qPQ+1kPFX{ysDg`S?3]YGBm`N&amp;965^aTCLBM=y?kwm5gXRH?awkLE1Cb&amp;4R+1Yah4HEcJdo*D+DvA-QBB{-TV,['WC0oCKXk.^!vTHub43s[eahTBOLLL7=NI$(1WHh6sU1.C&amp;oTx9idqPeo8T*=Q}?iD4ZV255}hDwyNZX.m&amp;zaEZot_6*w4db1'2Th.cafDAzy1n{2d%{@pP*BB*!bEG0e0p%ni1lsaNApoIxYBQgkO]G{D{?]rb4`e+u&amp;DrceUsc$Ilk,8fkW$&amp;IFBI3X%O(I=MSw?r4?MbQlANEx*dksHj`I2Y%8((-4F2WIUg?FH%^LfsRX4Y8oF6R0d3Mj.jC,rD%V7v@*FvnAj$u1'500VRI`?-PFEL8n_(9Dt8sv8syNLKr)CIoCZ`[pT!SZ(m7=RnD$B3z8&amp;38{*,PXUOX?fD-%CCVE-uqOM+7xV@ivL)T_DhIDh'xQ(V,@KLEy}Y6iFq7!@wV9s+Za9LHX&amp;nQrC{_=EJ%BbFNu1Sj%`8'BEG!IdZ`Fbz%eIwn4yFHCBg,+jTcZ`Wn4mbJHU+^zAA1o.3h'GA_'L_leYLAaEeefEEI2!=OT-+vYyW3+Bw9ZbrW@Cho8sSVLMBBfDTGak@&amp;,O-gBErH`rPzXF`.6m-euqD+q2-RUDQ=NC`3PX!rTj,un0y$4KtaEC,]1G*`niX$UoK=[5JhCDu`NaF*!&amp;[.@9,cD?QTKFS,=.N!M~WQx[{d&amp;lcinD{]Hr=.XMmI5Cbmf?BmzE8L'rEH'U+1Z_uF4(CD0DK.O%y6n,R]D=&amp;~d-m1?CgheG9BQku.+Lk7j!3f'D0Smu8V}r2*Y!%cHA.nOC6%[U?HD*im^fdCZTQK?CVbrumilZ]1!d?JhJMKWFy7sD.Eqtn5A!40Yk~`bF{{6NzwA]Vvzn=eB-zOjBWhPa*&amp;Fd$@L,d2@AfG7DpGos*R^5Lf?gp=gy[xpF*RcH1?bb0EtHb?^Akp.ETfc_f]H8jcT)qd-sI&amp;[EcCNI9sg28b4=^p(WyGDE_E@v=E]b!ES)ve+LEgIEF^B@L2i*+VD3b3CfUNsDWjUg3utbnNoC2'Jv]z,D*8o!6M+5_QJNhHlF,z~B*cj(N4K%FkZd&amp;d[^E]TBhP7rN^E$.=D@DS^99uvCtQZa*+y3gJMuq-5%-mOB5~I5eKMDFY2bk{,KzA'BvD5T(9SCxm?F$.ccGDMEs2hR2^YSsE[,^U?v8NJD0N4DDVIPCS.7?`u!7]RDI=FI!Qj4RJr%oUzG{6!C+d^'h~cRv'n%MbMs4UoFxX269-K9'kC]'=ZNeUKFKJ]1^r*8u8gwOxNG+.wC?eQgEB7*@LXP4T${O%-Df&amp;IF313kjDyUZ9Z&amp;{aeFXFc+K@rbi6eDGvV.s*lDWaoRrN~D?G`OX(rAtu~Ee}4Qogan3LiNz$2t^,mFvbh(n{r?]VFe.yK.h[gDDL]frOb3-VhS4?^.RdBCC.lQ1.fkOiI,oyA1OSOD$L8($O}Ho&amp;$Jsbft3b[C7tAyc%97DlkQ,Qlqw6tE5WZ41HcukQ0-xX*hKfTDPbYOG(F7az[%K1zV@&amp;YER9([c`8ZF-$8KZ,plhjFS3&amp;(XfAA`Gd(bltTXjcD1v}WEbq(QSidZaxfWxGE'i^bSuO3BJp^y(8!rcaFiGN}8^MoYg6Ror2J~f)F*)E(@lstritTmsChmZoEbf$N*c}y}toxSrBI'hJEG}PH9'?c!8?6QOo5vliEhHfpuzb=VI3(Fkh?sW1BFIJ3f6MF'Sf}MZ'${.[Ey.7Yzvi)k4KS!=5NxqBB=TJzeKU0XBZOhzYWq3OF[qY^MLGjOK](7{hi`EQEa]}Q5eYxOC0~Pnf%'JfE?d(geL[NuUJwGWQ}QY4FRuK{eQouW7cwAXgNAa}AR(QZDOd`p$rr!Mz?locF7U&amp;=ukPU2`*oQ0?R1=NEu6)zRG)O^0O`jhwV'.PBVEBV+pYmzih'Q$xa0ToBDH~L5'xec!xzlfxxdh6EwfoP(8wPr3K*4'$@9BHEy7QFfTw~Ei'U3m.[P4wEC@I*IV+Fo*aBJ25-,PjEYyD*ptL4FsJ2!kKx%mKEENKkO6dKl[PHF)],ksoFF]58j~8^WSt-{)R-QB3Ek}UgN@QB'-Ys_1osNzMCz^1@Ju27a?W4R_.8i]tB?$jVsCB_b`Ke]?vA2.%BSuA069A$7!O_ih6RMp]DumYK3-jYX(XMs^s5-YuA^9Dl).IQodE4WSEz0{cD'TG4ou1B7BCS&amp;8lUHfGBH'ScO9Po7lved?I88*ZDb!,UqSE&amp;5c-dX{-XO]8Ct2k`s?6~rF9PiRi*7&amp;7Bo9$.4L[7ui^jZDLp.liDaQ=x8TGSOBp0'aKk'D.Fb4=^E^41YY,U*ovJavkCVC_$GEjDzRS^`.fOl}FD&amp;}&amp;~Zfl`NT6[1t!BqoTF?k^(vxlDVNTM+,baVY1C1O-&amp;{RhlLkE%dADg'CqB0Es5a8T6E=q?G?&amp;EghsB-plLtW-4LD+$`5m`WShBZpVlh'C^6!8Uk9lM5AaCP9Xi9sX-NpJl_8Br8!0C!@!5?QeQAQ$cGVxEKz3CY=)W[VoT00rjkEs~v=xBa$[VmY1B]3053ZUvQ7JE*RY)vl{](j(CF!g.+YdE(AJ^5Aw[UhTYPOb}79FFzb{1HZP]Eq&amp;3)(*58!hBQKSy[Ipgp3d,V(`N@WbFJAk!uOsk_.G]4$0}Vz~A)}Luh`N'tO,!,DBU'(qCB-`j$9aExwrGhCE.,ghBb2`Jpnvr@uMuP]_9r$iFTxWT-b^mliUHqoR3P!bDe?+3cr9rX$!VKi6-+eXCrgd3nZC_H02),GaOP1MFGbQahfJxGXLTjj%,cIREgbX3I(U8L)s6WUj)I%6E1S2LdPw5j!*laCi%1a~C44a4?+ArnC7p,CI]M9?D$x,s]{PpnW`&amp;V8OwiBHBhv})ddVjuwz7+tVcs9qB3EF7aO$u!FZw+4]P*I9C'i6GP!I}a%AJWKy?}DqA]$Xyop-k&amp;4_*&amp;.X-DF7ET?M7mko5o!d8n!'^X]aCtt@[jSjKM=1-Oj]7k,{Byd-OQ@)iF9$c?30cU*+F.$b5n2f$PE(()6[WjGhC6E9WPDmSlNksKeHkIk}C?pksF2CQt1H6WMCB2K)D!OoJ@PIhbGw^@E5SvJpBZ1GM&amp;0[J6l32k^WPmwEFfuPBE4eQC$ogH}`aS@gEdqeL$DTS0OAyD5AnQwzAGRu0uc-$RlYNCE]),EqE},bb?$IAJi_RkM7X!f4B6~y[kW]%^o!rJfeX3T?BeGT1[C_NpFHzwNpATnUE7h^9Q8I${RMA143Sm7!F-o'FdBB2gZ4Wa-UF%Y%F'nmmW+CzV[}hsYP~xvoCyE2!es0kOuG1VaI].^*E,9~TKqOe6_P8YJY$vMoD_8zNCTZl_J96os+n(3(BS88=B$Sn{.Yl2xvJE,LFJqhsBzPcuZ)e$r(ds^pDr*YV.s3_Pa$~Q-R6((]BrVfW`%M)i+vJGot$Ri]Da(5Jor{Zp8&amp;6Ey(}y&amp;lALUb[x.97cH-n*=0Q@HgCJiaTj96i[iuCFX-(v*yBo1%A+n}_(05UHuLu_dSCh]@l'y5Svragt$I?Xs~BiWuW0O`rb2=)~uLJ{5&amp;F4jf_e6cl9C$o?IQKN&amp;yBr??b$803L0]5dUw,]AuBVdX.c)x_JlmeO1](hz0BY-hr6!J8~G,r'fQ*-88EMx!0i%F,E]PVyE.mMebCxowLGZhA{PIEp[u3Nn9DxR7XIpD!E=[WKIl-Sy&amp;Ba&amp;a5pwZG4jZ9vsct^k'FO$~NfMlE-FHQwHjJj6mF4xSdsIO3b-$B.*CCkk@C.P1P[}j!)gUqkt1*,wbC,Sbu355m_rex%)$j.Y2B5mm.CA}Hf8v,PcyRm*gFV}f$Ax?c7,K5C)`PCchCpgW}Q,8o9suryo@PyssE3)+m*'30?z_pJ*3(V%MDB+^xB@``yW+cSlI}m'nDf?Vk3y0,VRHmtUvha`yEhzAREWtESz@Bx7q3,yPD&amp;RpevT[{9KVe`VZ6J!5BF}nIpWE@}b=hJiM465xBRYqliB2H.qy&amp;A=X4A(aD3PQl7COAUX75`A![~^^FRs)dgDQg98u-ZhuSBCOFkDIjkyU^&amp;eR6L4k]GORE{Xcp^$55Rgv_K0CoLfrB,.[legu0e'o+B%^84ALFF*Haf7,fY2lk85F[1[-B`610JQBPggYY~~O~G9(FB?eVw%y.7P6!~ihav_LB^jRi[vm,(fE$?2E8Yx=Czg65giIsHUhviDC=%?~D04KRxDsf%`vS0kS0xNjA'7j%w2k._O1)'?={wq~Bi&amp;ngS`V@oz-fPIslf(rAk1agN^~%?udM'=Au&amp;p1B1*F&amp;Y(jn&amp;$`T}0_hd]VC-Ml-U7Vp_XYB6!ds*.+Bk3aKktD{pmzf90PUr-UFo3AnwIv^r5yQa=BS``.FD,16Brfgla^AGH-}58.B3mAt?^Gi6'&amp;082Y$R{1D_!Gi)EejWYU(T+p&amp;iSjEMGbEMV+GCp0LZBIU1y&amp;D[c!qb1fms*O`%{pRQ*)BpIFjTEk`UPA97`a7d1TC=gzDmD,$L!N{H}P6T}2Eam-bL~M81a^Xe^a=_nSD~ubEoGd%Z9+U!HYp-T[FMg88ja*unyA=N^XcWvSF1vBGGQ=oy5_x_PZ&amp;e%YEl`i-$,6kglm@`{k8t(8ET(@*RcdsR2-(fCW$@*mDD]{FA)5-IfmpANJk4J}A%x~sAHyw+cf0vMqBrCDEwn]1Y(=no8dq&amp;yupR-6DvR^u=R4WQ,(X2xe!J(eDRinC5$9UF^e]cf_kU.aEaU`(Cg2+a1Z7+JL,lYjB+(S*wz&amp;PNX9[Gesq%c@CoFxK0&amp;GA7f*nSk$L-^)Bl6(Dlt%{YgqBw]LiPghEhbBvWuV['2+MLP.&amp;dKnF2L=mYExIO+vIG34J?z%DdkVT9P*ZOf7fU~k'gZXD'UkQO_e4=G3Ils6Yc5+F5n+JJm1xE0ZW]a92VfMER6ALCfk8xP9l=b(j!fbC0fA!Sviiv3f!3*-0vaKC+px@XI56XUKUX=fuycgFR$`KJd'B[21zru?}gtkD*09=r.1jNxa3*BkL+8dEqHNj1)qHFfL[CmvKq9?FWS,JM.Wj!+=OJ%?e3^EF^0Jjkn+l*amzt65b]pXC8-@F){rnq_d_SSELmPcCIyS!Nvo)qEoxlF74h6tBDTMSg.){zI@vtIF9Ik`Egr708T=n?Y]t{?VS..QBt[N$?NpaCm^Qfw0_4D=Bb$8f)x[`6MaFnca(TJKBO=(VozaK1R-1WxKhIcOEn9I'orMBCKcXT?My_)9BGJk`.,VqFe3tgf*KKT6F(DBDx.l-kiwXobX^nHBElrATnk6Zix&amp;Mh`_.byJF6$D?IMqAq.!fiqMmqw%Ejx$ywX+DqYK]OcP_p{cE&amp;UHMA)YbYw4?l~aL7?=FUmqp4fDZH1CQE=g0t!`Bc)g!Zbe.UI}l1dhBuXdFO0UvXYah$x_C}=(9%W@Bu)`!Xmr72fAjkH6!zyHD`UPa5T%=Ha+(Z~Gr-wUERY^KgnG*UL(Ofhm?N*{BQf_9dgwhy4O`y$02QKSD3?^5N'=iX6-&amp;IL%ekSCFhOE)63e,*?.O@fEpz%*C)b8?![FZ$4RbdfR=k7GFSr29{21lWCH5h1bTRl!D1=EcXk,x!DHxdtWo$.+B!5,0?In40-skK0m6i1bBN_@p3~Nq=haQxFHkDbHBN'hJh~tRtELM9E.JSw)BdIOEz*(@8Jn-%5-moDSEA~hh0y_OEIcho%OZV}~C9.'Qs_g1DoLvbIAo%%XB`65!F@bBF^09`v$^u]?CD41fF=12EBCTpL?9r+xBIeB)A.]QoGNIv`bGQ77E)+BjE^T.t1Je-gJI'mwB*rD@IX*n-9p6cn=k~}zET!W]][N&amp;w-~k+?t*v0IB!@*E0Z!Q_n1d%Rx+!0`F%,_&amp;St9Fi@s_UM%V~6LFt=PVP@N1$(7V&amp;JIrLIoFF[-auQ2rNS?O%7iG&amp;h]BbJSpnI=UlBAJENy,?g.F7wFwF57[A^jfenS'HbNEvrLh2ddFKT'(2D')9E%Cdqf.S]YJvbf40Zsh(cfEXF+z^IT~g_NG2!1v.Z4ER~@zD5YR=YEtz=MIi8{CB=}`jY3zb_iGmfZru.sDlR?][)qM2]{j79l2LUjBs@QWdQRK'D@SBxjvcJSBM+a`Tc{fcHfT-VO~VxZC8?[rzpmP]N)w2wf-W%=C$qLv%tbWrc9=3$UZrx_CPw17c78ymo$F8Gko_GZCz0Y$GaysY(Y14FuwHk5CYijX3XHZ3X,%lr^^7&amp;NB$'7zE!6R6UUFBL,Fn.iAt!%PVWW}q)q@E@(vYZ,DAy%k0I5hz*uG8f$_&amp;AVEf+q~B~uUPVj]X^aFKd-E2`MdT!1=JD$da^hbds0FAO2!()z7FG$wEYX`(qJEK,31K0ld$1k7Zdhhxc4Eo7`B2mjR*3!d8z`$7x.Dbrc2Ke2j-Q3tpSDpa{mA5W$Zoor%_]3T]cShC_]DXxK5kFFa%nu'AZcve'MC0`LwsCYokOBp4,fOwPnC^@&amp;zSw03,OWGY6Y0y3?DJ{Ww^K8Ze,Hn9IN4_7jB'pO2e,Uve8EKZ&amp;w$V(2Bo=75!^hV!dxBKa,km6-CZ)F[9]ozurpqh^Nw!`jDK_eM*k]dl]v_R`S(rsVD_A~v`6N%!VzPVd@wwhKEf$^$3Lad)qFF17Uxh*fB*t&amp;7l?*Ht.5qQ`M$0'ZDh.T,atqc%&amp;fBDB[mnL`CsxXyDoHc4lb3~%DILpnDl.*r2_,]l'7V5QB%g`pFMh@OpO,Qv1Lm4HaF$_XD7t&amp;K+4tBKq0h-$J?L4TF+b=^MGj=1CH&amp;j5B9_vmE`uP~Z^?Py${nafDkRStE!h0XMEcH6E*hVAn0lg'FPl,vgsAL4RNeN?go8n^EI@RLdj6ns3pa*V@XsehDNb+WX@6hr2ll(2nV(8dBL%,l8`_4J=629`g@~,ACI38{p{lQuv?L?1[6!k!Bo]TZEw*oJv1{6tK-DuFCLiH4iyXLINxi$S+j?}zEOJ8D5,],%4G6&amp;3BMb}7BG.)E2vTXyaY%.x'udNAEj}&amp;IrcPIn93f_^c3zpkFDD+%{A~gMgn*Dc9fQ0*FjVS?AFc8z74iJ1UhE_$EKC'mh5gSLz0TcCCeYpyC9V]IKcG[PE.8i{00'~iE0Am~6zgmtS!Ahlo8o&amp;DF3@(5qc(BW5V0C!qE.=_CZwTI0+X[oTze24Q'x[bBq)VJ^y3D3^l4FX7L[FoAOhHPG513WmTTlA%]rfGC,W!Q!zr[PLDzdN_n%eqAnMF{M_7S0,Kx=sj`)@=D8pHN@vXZv@x`h8pgw6cEp?EZYrbXTD@x2gy'Y$BE!Xds!8n-m4G@%c9)BeuD*(z)D2D2?cA.UB_^e^_B-5WEJ^cV4Kn?%a*rqMEDm5cGE`t,?f5'S'j[lt-Dwo)E-ieHAy3rDsA3h%bFL=uF@xsb%K]lyCA$gN?F!W3+_Y.Afv06GMUn@zXD.fCFrP[YT]NI6tm^&amp;eCB_lgwKH-2Vd3y'g?W1CuBQ=Q(J.PZ+IBY3oU!NXRF%@nlvV@'J$F`&amp;tPRP.mFvy+]jjpYm(r&amp;{Wqm?gKC?(R3+q`-yt)sNWq'3I9Fz8k$HJ0Vin}%6x%il$PExe^[%8-7]7EZrb.)%K)BR2M!ubhKgQSyU!OoP4kB(shtk%2mhS4*u'gtQcMD_P-Aa%T)vpYhIsJecq1C]4n^aYqW'3&amp;30GPmx9mA,6G.hTOz_7,Yz3PS[=hE]!ejVFLrO59FnTM`JsGB@cJ_qb-QXtcoE^Ywm_XBk`p72(92{Oy.29gDgQ~CKh%6bLb_B82yLbTLzw7D&amp;Nuoi(l+(X)&amp;?,042ceCsN(voSVKjTE6+l4,vy3Eiyk4%4]Y53KW@9E7@jyEEYdVx@U?GX*5}{xDjR?Bir**c}FvmG?7Ig=dq)UE?7`l-WyB9]s,@do,'Q*FR{+29ussvO)ARpC4wj'FywOC'R`.%{nxnFS=B0oCcxLs$J)rP%ajLl,?2K?BUp+^RI&amp;Cr.!UvpbMfXfFG.U)ia7DTo710HBuZnhDLuYb.5n^0j=x2@LGEfcEtXuGdhHU)h5FU,?cwGjAhO&amp;Q*2(H1nUF-OZLYntE?xp6jLxR5aVH2v]%9$yEs2)gt,R2yiT7r[FvkGID0+vRj$z7a@XrxkIo@txAWj'O'P(abE`FNl7xCbUEll`ViIyIa!nCouz)UjUBlVYKgtyDyk&amp;wl-GCBKaENofOxbnKiQyP&amp;vKVZjBESh&amp;xqEfAH7JCT+i70C8C%i^sBC__kc}Z1%9vG3?Bn1}j%Y[iv!?~%,RDME-FvcWQ^Pn$Nn2b0I9~J*$CU*UUG^}YI*zGw1tD*ZPE{OMht44DZ`[h+VKJ9nTCB'8LQB`RW@Y2QNizmXhD_wFEw755)3Ucf1M~z&amp;BDQ&amp;'A6ATOJCR4O&amp;eLd3}A=fyS5atp3I`Op'6V?lKDv(o^`,6KVv2+jfJOIx~AIPi={EMgH@WTOly+A,{Dsp)fE_?5k9bSf1zHjx%Bm}+-d,hl-r?)xr(K7yCCfGXsL(DSQC1J@8xE[NTDeu]2nh~V[zkok]_._!qE)J_u1ZQ{7!fIbmI(,?8Fdfz&amp;i3J_eS,_RV2R.k(B]xMZ.?6xt4Ex9kaJRxfE_gSO)CaQo'7fu(bFhKLF]iSq`wK,1@jpoCb+oy(Fc.rXf6P[Y6BGc,^Lze[DhddVE6{xevCI&amp;nQgu{HCh.934?YG)g{w7_NRV~'B+k4EXe!O3**M[[hW-Q*D=P@0Fi]fzM9!{yFxO$AFJ51Sc@sufQ+]i'=vP?XC^]mxwn@zBX(h7753_&amp;UB4YyI8zGy~SKAPv_J!GhF=rauea3vl0Jvm!X1{}PE,5On67wed81}w'0IjS!E4b@yH*YkO7Y=H%aOs+jBns6M.T%LG@'^I$vvMr?Eby(lVz!kPG]o6cpP_h5D~K0_U`@Wl,^4eS!`N4dFYZS=?a0bqI&amp;8e$J.IiMBn&amp;^`un_MPA&amp;`f[2bt`%BiiH]Oq4r+3K%gJ$i2}wD~gg,k`cTD^^Zo&amp;oq?7bF=lR8T[rpAJDS@&amp;js[cgD_J05C}3{gOSyr%g)3&amp;aByy[q*s%635?lo5`q1R3F53opsd3ObZ6oZVLEW?ND=lJVH~9WXn^Hg*WS9&amp;^BJNX.jE][14MajxEfyinDy[F~tyG7]@nNHA'Z7j_FpJz2O0m^aOWcp`0S`V7CM=]ivf]v+l*?ps)D98.Fz0bbO$f$.6G_-m+i&amp;eiDs+E{T'n.J'c{Eb6R,%eE[rqid6LO^D4l~Cm-i&amp;IB5+`xe4^l4]0vKWxa.R&amp;CU&amp;.cD_S&amp;*ZpY&amp;CPmYk7BE36I4`zealkoTIXtK2NBd(Yy$9r*EFJdyOnXpvOExu%}?A1I7{K~YBU[e%@Bcvox1y!1_5NPJc(%6wYC1E`+A19*H(P4}29dE8&amp;FnJoEJrME&amp;x?po}^~[s%Bbz&amp;Lx8JhR?US1Y+hE$cDa8!^Cy02b*0kp})x+_DC~7@jMCyTNw!h%Hm$0%1FOy5w`gqb~?U2&amp;P$v4b}Bksolft)P9?}3)ECV[p@E*z0xmC[1Ops!eO'kB({A7WTb(sbrKqyTX5F)m5XEa(E98_Bzetf%WnF6Tk4BjX?AA$[F_sAlWQ4ZoPXBe[hrY+-^GuNY}=FDvBcFp*Z,+irpzX~fq%RXx9-DpX&amp;']6^IuR'sOg1fYRlE0kn+I9+yW(?[D93G4v*Br5%@`w6*1+iikAr@qN]C7~I=ggsEt*0&amp;4p={~tZDIc.B.jHClQJHhmD%ziOB?ym&amp;c2$bzeUApRN@,zIEC5b8hU6Qf-HAEo(QLIKCd+XJxiqum7g2WnSh-MCC.~0p,w`)n(TkPd.@DnuA5X^DzA=CR(k5^Xj_uDpBf*U$=cCEYr78+HwC'uZF6qoeeA}wp]lFR9^0}'IBQ&amp;VsanaHNo_{5D444kvDpiD@hqzAa1XY%S[8!JjB&amp;Q&amp;ZwhBUFeKN1)llj?+B1%6iC9FaOX=dHuo6.EoBQ}0Vh6d}5{vs{hjwVmdF%X?$hut]]P-UXA!E-j^BJ1N=(S`Eq3T6pSX0M4pCilvG0dVG~NYO7Xd(kH[D^*iwk+G4OX^@}D,vL.JE@'6~bs40w](J6WOSeTzBA*clKh7S(U7Z0@uFz6FE]FF7Up~BPN2n7O%*DM3E8*dCECabO0u8$E!&amp;YmoBt0MUl.+uS,[ACPNLr8fD]yGDB1Nce-8sYOQPGteFZ5HUp-.@&amp;X'h_I2f3HoEnMz?$9~eT&amp;a$LAg_4FRCFF4mOhBofL[5tFz(LdVDPXFEjnKi~kSNG[2VY)UBvo@UH3t~DrQrUGJzG%eDjnM-?'N8e32)+E&amp;d1ECBNW.BDwt@9X)j_Nuz=7BEO!!.,!rZ3+RLGS7GqXWFFI{uzg$t}HJ[!ZLRwBZDW{pJ]tF&amp;X$%=0iDUS_AEE1z}AiHSgtzQp*qO'=VF-Zhee'P*$x^IoBFX)k5E+bjA)hWixt0Sk$A=TgZET)U6FDk[dI?'&amp;ulXv^nFo@hYz^[{D]n.UVbk*d3FwqrIkT(K,Y}by+%S'MfAgOi(.{@lsD={s!+u=lyAVxG_y=gwq@=RDKI?u+bC!R`?R@flq^t1N^U@3c2E6`[vukbVz4p4(2go,mtBuVm+9{q{raGaSYmmo~aBK2K'6n3ETWJvtzC]Ph$F^`uMmaI+F(GwQj`Ko}?BRl'-BKM+3m3Dj5(5G8BEW%^BzDsWr7o+epBX[01BlVsMQ8S+bfabm?GJDp_BROVHSzG9VKZ.r1dpYwEDX%C8Ks[yR__l!uJ{v,RBnnG+`VvRVlj9%Cyq2VfDlA$rvBs@,?UysT4t*l&amp;DZ6g~jpZTntjF$A.8KG%C?vQGE?'R?1iO*o?p5*HFcC%,'@T1L5Hq`V^43iGBj(o567pkP-@^&amp;Fv*-.dECmm,otn!kbJT3nG6Qm%EbRU~P.Vq5L}CC,Ua]2)F9HO'.+H1eiO1PAR8@zyE(`uZ72_qX?{&amp;ksx(+hQDYY@qU'I=nYa]s1(xA6}Bm0BZf[O2SN(?o%3h+CBE%7]t0)tA1VU(8{qu&amp;K.E~ZqRFF5zEN!mD0&amp;v8JeFCAsx@tKMA&amp;h`cl.qntoA5Z6u^+0j`uNbvSXw!fkDChLkWJ^tXrY,yKw9X@tBb$_~s8mn(]CQd^Lu8KsCrIY+Hs*l_4cU~m`'&amp;=}Bh7_=d?,Wm1omY=tjvK_BFK)*pyAU9t5d[D^R{3KE0AVhq6JE?z4VH(4DF67DWqcv31'wUOdNvf0ZSYkCx.hi_eD'G03DhO7'Ce1E5blSVaatP6Zlkfgw1ACDQds68MO`$FNnLiujK(5EBc8bp4qZIJ.7=@@UqP-CXWMK,LO~4i6@uFT%x$TDXFskB1ATT%pr-cFVIQHBQ,E'0eSmFs@$ZbpASmIDG[]zUd&amp;S_[sLEVV_F.cB',QLE__Cer&amp;@M0hM^2?C~4-Wi0[).6]2}%paV85B,+eJH4LHAcdyefbYS*pCn0&amp;VR3p~_y4[tWib=$FB'2Kbyq$+ZSOpZ6Hm!?HEsp&amp;W@*+?3JZ{B.nS`OoB7&amp;QpCo%'M5!M_pI&amp;WM{Axz9~t&amp;nsVO1pBl^?,L3C[nCkGft&amp;(m~iBzVBe,]C3q?qB@NqB5-_+khBX+zDNeK!g4%Jukb26Bpw-ZHC_]L$0YL*!n3PN5*39YmA3de2C5JwkC}kfLV13rsCQ8Snyq*AU(`G+i^AEqfD~8XH,-Dmqh80+_4E8xiD[vT,xBqC`e`r-5)r99JF==X[i+5]GN)G]hq-TkRCvUB+HjjW(+av3UgDsqVC}1LLuGuZto8ho}ri^KVBBPX_Ps$3+n}Y_mY)PHTFt7-Jy4(zAMkDNUyca8^B[5kFb3(..G&amp;u{BvJ2WVD$gD'RwVdq6`!!i57SlNBsJz&amp;K9Ongu?qh-SYZ%qA_bCRMkv(?XT(-XaY(9.EFWnct*?A2pHx?2[D^_)Bu(BD19EEe%7X^Uc%WkOB0Ufa0I8+PbTTbse{58,FDMqPEB5Oz=o0wbx2MF.Fd=ApI-xM]fsXTDMewdkFpmgnf9rw[a*FP`(+2k]C%5'+nO%dPnZy4}5OqdBB)K8Qr35niF-qB`1ai)+Bu?}s.%?ea?iD9Qff$_sD.WSi=.r'f$R=MoB2G+cE^aXENksfrW[h&amp;B.nf75B?v2+lw931D(B!UW-cQ1C*]h3GJD^EfliQkL~+NmD'WAKmrUKg($-lTVDW!VCA&amp;LuN^diViesa[sUzX*C,}AEhG1u9.$?QK3(KoNBNN%9pM`V%W*YKaQRuLJFQOX,@ML=lwpcj@cyH5[FdT!021*B5i?sj7iEd2BDZO+dKTW!mc,g8wo{23-EyNCcR7wZ]I{fQ_AvPJlCB2M~8VW)c,na*TTSuEuEn=Dh9h[29AuXP_0BTC,B}.}}Tdi~%FU+UqFi0p*DF?ZA+8i3!G?-~Wv,%!0EepC9_%RH[_7OjNP71YyCXDdOw}_)=PkD,jko$eiDwMhh.oRmo.B?*tJhwT3D2rFuA9lhNz5W2,kr,lFB&amp;J$&amp;N.-GwydbWpI`2R[B9t(H8pt3jdPE~aNta6LF$IBj@IhjjE6,g=PwVmWE$w635a8A)pAU(Ug].ZRE_wd[iDdHDF=VYj@Qb.GE9@%EoFms*&amp;%,=+Rc0dnEkn^@%B9+sZ-'!VG`)3`B@m)m$br)l$l{vKp?8+1CzE{$.qS,A+lWA)bRoJ+CVl)q[5*l7iRO9i.6u3?CKV.]FVHXhhfYD[3kat5B)i2M&amp;?6Y8={1[{pROpzAvK,}ID4L-We)8[k4q)wB=IHz+Fz%w8&amp;,h}@X?W?C-X{&amp;nlQ%).LF5]YGlnnAgAO$M}M,&amp;.?QH*_OWO)C25n4'G7gaN$14o)ndvmF9PRcH$ew]Q50~GZYQcbC2OGCIVj@EZ)AbQog6pMBjslQ-A8uZixaGJv0LVTByF`GG*t]cEdPl[fzb[dB$mhxwyQPX'd%}!%g[%dEQ++hxhx5.uI[(Qzg*djCZD{4USIuFeER@+SIeGCCT4~mu(Kv0VK1ws-ehfhBq4dSUdhSKAR[bGzp'D)Fz&amp;qH2s{6$cf!=qyzCiGFCig!G[1yP@}=g[SsvYjAcvssjy]9m!]mV4YBNK)FFCz$MH~Ff0}$^$G5^sOD4rf.6mHy.*fMcPr=ehqEww(-&amp;5i%yo@[nHtw[D+D[33}[shtlA'{VBqJwigE'hQD@6L{MZAWNUV3?8`BtgIXjjH^m4ew8Orc3qeFMl8k.4uVB(wG2Vk,n!AC'ZoBN!k^svXR$aah`btCO,OP2~2`hB7e@1t~NR?BzLMMBPR)z4I)mZG4b@2F4aqcs%?Pk^P`0Yj0[fcB2jVds*gma-`U[!okLzzDr+sHZl3,]7`u8(YaCi2Err(X(N9!pu=Kx3&amp;}V_IDI_-(kPxf(?B`0y*ldPOEwfflhuE-wfw]GUZi%HDEI7n-ut8WA?CB050HO'bE$5w%g{*=cF*%u?p(GTPC^DmUNM}VSQN9~te%D7hE@l%NxH[l2Z5%zF_8mA3D,8,Ctg1vtt~FA]m(p})D%A]KvVIfDmt.[O3F`M5B4)%CcAM@_S,]_}D.Q!=BeG'fdi5wVsUK!aIzzO%BSTa=?aF&amp;NO!yy`MqQdVFHZ%H8L[iL*4`PToG_uXF29!!aLuF7KxkvA]K^Z^D?x0gN2vHtWQUPi^=c&amp;@C={RlRy.T6-$+PXHPQq4FzJ,7ea^x&amp;m5g1%]Gn?-C7Lj^sfLyCP7zs944F[)E9[?+E`c?h4vh251{K.RF`0',N,,O{_+PQk3@++hA-vTM&amp;xWvblBJ,KD)qJ?C8TizS6d7oux?.)mEn,XF.,Lo$&amp;*ylq0Ml08%oM,Ds9`KV-.pWpP.OmvC+I8FSl9S8hdX[n}^2vIU-6aEdH92cC!ixBJ^Gq&amp;jAFCDF@0f(E=[0O'Xz&amp;&amp;_!RfBx~JyFDRWx=C+[x9sMx3Dz[PGn&amp;MYq5TbfJT6M}6Bz&amp;M?*U^Q4NoGc?-56MJFf*2~,2Z*CMt%a!p$L63C6ei.X*fUW_$!+3,Wc%pCEo3R]B7V)?yf&amp;L1q5k.F.uuZfH282tkm_k!0!eCE6XUy+(us~rL&amp;h27IA*,C5!'8i8eU!,Ri6`pgYgIEf~V%er5FqoK=j{QYi-?B?pouctcM8XvQTo=r)j%DD(,)3I5z)o1e5z+7STaBSqs8.2}j0SL$k%i@5-rAQuuv-SU}qAK7I1P41+5C]n0H=c6,ByHE^KMI-6^F~c842&amp;,)O9J{Ve%3$&amp;7ET3Jps{f&amp;4U[`pRvn*$ZCpV'KLGcEZbGdeEd@?SeBq}8Hd}TSzK@7IjaOCcTF%3L1@RZuPmV1`K@^pqfB0LlcR-fwS_}u356q$K0BjCk=[`aPRQ7*-&amp;Qo6e[C)p&amp;{bP}ilcKkTsR]60NFbG.+sSI0TU!I+XrJyt?E}NT%R}K(g@ZizpB?VclDfMIc7'7nDjvrtoQ[2N~BCs7}-4}kCu{g`otz5?2C85jdLBekpeeDcQGXl7tCfIz-H1wDdk@57@gdb$PFP+O_`6+o+zIBtS[sC4LD8$S8z^^ZkywpFqD`uamFvDN0%yNhtN$E(@r%()%Bk2W-BQF]S%onKd?Blt6CC7s}go?Cu!3D'__-NUYFHZ?=JO9mKGC'C'y][~lC0fK4{dy^}r14nwneHyJEYzbLW7+f^V?$jRT(7XoAX4qq%mbTz.XKln1l*2@DB8DNbK%$+N)hBR1bdM6Bx^Xv$zhfbSC6xIG=iC(B4T}(VMP~wq)uJbd~8XFBV-N}jTkPXv6xtFLh9QYCsC`SGN7jo9}64s]_CeMBhW,EtKZGJPIG!S!qm^KCa[AYZmd4ESui3kNmBdlDoDF2%wh?l+`&amp;xnUtBo&amp;Clc?~i%zh2^Y4$^!TZl0F%5]({PUV-pihS)z19T5B4wmxNA4tp9y%UtCDJQHDGf(_UEOCoz,^QiNa0DQDt{o_JMNvCbaKack+%%WF.d,X.3jB!$Y4w@[oAHPDO9wFraj=fx8jE_sp+EfB@MFye*AUM.Di'$jxD=vEmh8{XU?&amp;4)7C6b6U-GQD3D$vV8!w5hR_s[b!{2FCvC^!xg1Qe^y3Xs[qK6(C_iA&amp;?_wc!`ReuVe[@qjCS))D,VY!fG[}50jQXFLEYM,HZE$&amp;Mktuxl%[=!3CI!,QJ6117JQdV4'Z}7LC497lGiHj(026LpJ0DE(FHwzjr2S&amp;H@*.bTdLoF-CxX!rtAMVsVlO-n=6&amp;DiA,v]Z,)c2!hFEo)ufV?=B.AfB$^9g_3qmTR[y](DDFnZKHg,hoPrsz@YstCtEEbkAk=OM,HvKp'fay[hBt!Jlt?CMf.]E}v4d=r+EKW0rZ-aW@y!Cn5[%]T[B01!WS-iHGBPXT+tV=*hF]6HQbtb@Wx,c0Bez*s*B+2vOa.s%JYT[r2P+!rED'@8zA+YBWm4ct?S6GUpEiaVz._RIYw3hgH0C9EeELh7[cEQaSy6=ez`{E&amp;]D%CqY0{-B?v+fis*FpBkE'rfFpA5o.)i53^[Ps0WDT?XQfWQsg8{rjYY,2NUB*VH8MCRB,Xtg9}!9ItlAPZy?YOWC6=D.wR85XX(Fb7wTmHsBE'^a+kF'H6+B`ut~2ZOC@z0(J99ar3ZEj^11t%{^+zOT[p^2{yOBU.muv7!b}b,e+5Z76-PD3[qgKBU^U*G%g8eI5j@E46Z=O*B_lZ.?Yx5+[9DDiRPHwELKg[&amp;VM6(w5n%C^~+BPi.n}%[Tv0w},lxE)ri179TsR3O(NQjMI.ACOLX^ViU,Vmr5B%9L19gBw^uNJzT.SiRX!]l&amp;z79BN]de6fGGoYJ%S@)Bq7HCZ$flG)rZrfa=7,Tn,%kCi%,jW~iihj$tH*S{cHsC7jA=!mNUS(B-wZ^Wwy4FM~+4-xQg!R_9)kyXTRnAB.rFSL1n!o3jJgYCWL+Eb*kV2)q@^jArw,D}[q(CL!L&amp;Sf5t{tCbf=s1hI-CfHVwlrN)gRRJ7t4T7vmF.2dk$f58tr?07jv3f`SBY?_Iv2x_PPDh_rxw.}{C.$Y**m{qQ=2[IPLmth,Dz%J,txi$LhQpBh3.9NsB2T&amp;dCJ?DP%NF]{*IFAzCZzgu[&amp;J5}sRv(~[={3BEkubUdAr1B^`6i^45yjsEc%(*pL=eM2E1%IuuLx%B2B-VpY(4wQ3xW)Yqc@RF=3sbK!c*^@DXA,REC[UD$??h6iiY-v4-4'*XX*ZF`vyOmY=cSp`.DUX(EK-DhUE'i6{`m1EI_66TD=EDIQeV-P%8s=^FMc8V=mFBDxOGmw2EvAPHn[WJC_NC.{~R5`7(,=}UM&amp;vzlaKD7`6uYgW&amp;K-whVoLhceUB1H]xAkFx')_JIML_CasBmwnxw_{@)=+E6Nt@oS.B.]dtI*pW(@3=VUe2F&amp;UFE5aF@*j6Phg3os1.J!kE3a{8c4}7wO6ZXVLu4[SCW{t(*B)MKijFQ!Mu{nDF=T8iQ!0Yh)G{GMNsNdcFNt~`E(?nZ'}ZY[AJfebE9g19{Gaz!yN1cP`3YB$C)3&amp;Pz(Ee}]-[N&amp;y]=85B!oZijWDrP)hzPNL~-LkEnM8}n1&amp;'1[S22_Y~1p$EDWq6Azc0{?Lj$u@([$I9+1zEJR*m=MFYKpI?XGpF=,5q4'$`)b_5v3fKzBx@0xE5v$pl8&amp;hnR!K~a6aC?t2Bb49OjT</RegistryValue>
  </Registry>
  <Registry>
    <RegistryHive>HKLM:\SOFTWARE\MICROSOFT\WINDOWS\CURRENTVERSION\INSTALLER\USERDATA\S-1-5-18\PRODUCTS\008BB29E5CCB52C41820CAC2B3C7C7E1\FEATURES</RegistryHive>
    <RegistryDeleteParent>False</RegistryDeleteParent>
    <RegistryType>String</RegistryType>
    <RegistryName>CRT_WinSXS</RegistryName>
    <RegistryValue>_j0,Y]s!Soe8MkbIdFwUYSru9kBp%l*9MkbIdFwUYSru9kBp%lu8MkbIdFwU%9YbWIfIbe?9MkbIdFwU_j0,Y]s!Sou8MkbIdFwU_j0,Y]s!So*9MkbIdFwU!N0,YT,$So*9MkbIdFwU!N0,YT,$Sou8MkbIdFwUa@0,YF5$So*9MkbIdFwUe?0,Yk5$So*9MkbIdFwU]A0,Yx4$So*9MkbIdFwUe?0,Yk5$Sou8MkbIdFwUa@0,YF5$Sou8MkbIdFwUXB0,YS4$So*9MkbIdFwU]A0,Yx4$Sou8MkbIdFwUTC0,Y*4$So*9MkbIdFwUPD0,Ya3$So*9MkbIdFwUXB0,YS4$Sou8MkbIdFwU&amp;vv.ZiM}F(*9MkbIdFwUTC0,Y*4$Sou8MkbIdFwULE0,Y83$So*9MkbIdFwUPD0,Ya3$Sou8MkbIdFwULE0,Y83$Sou8MkbIdFwUEgn.Z_T*G(*9MkbIdFwUzH^.ZJcAG(*9MkbIdFwU&amp;vv.ZiM}F(u8MkbIdFwUEgn.Z_T*G(u8MkbIdFwU=6U.Z@jJG(*9MkbIdFwUUQ^.ZZ_AG(*9MkbIdFwUzH^.ZJcAG(u8MkbIdFwU=6U.Z@jJG(u8MkbIdFwUUQ^.ZZ_AG(u8MkbIdFwUjN0.Z=0pG(*9MkbIdFwUjN0.Z=0pG(u8MkbIdFwU_iDv99TB%l*9MkbIdFwUHr5v9{$N%l*9MkbIdFwU4z4v9z_P%l*9MkbIdFwU_iDv99TB%lu8MkbIdFwUHr5v9{$N%lu8MkbIdFwUwBLv91)6%l*9MkbIdFwU$gWv9G!)%l*9MkbIdFwU4z4v9z_P%lu8MkbIdFwUwBLv91)6%lu8MkbIdFwU5_Xv9i4(%l*9MkbIdFwUIVYv90I'%l*9MkbIdFwU$gWv9G!)%lu8MkbIdFwU9XEv9FkA%l*9MkbIdFwU5_Xv9i4(%lu8MkbIdFwUIVYv90I'%lu8MkbIdFwU~a6v9)@M%l*9MkbIdFwU3Y7v9OPL%l*9MkbIdFwU9XEv9FkA%lu8MkbIdFwU~a6v9)@M%lu8MkbIdFwUGQ8v9qaK%l*9MkbIdFwU6-iv9vnq$l*9MkbIdFwU3Y7v9OPL%lu8MkbIdFwUGQ8v9qaK%lu8MkbIdFwUv$f.Z@}4G(*9MkbIdFwUpJ~u9(nd%l*9MkbIdFwU6-iv9vnq$lu8MkbIdFwUv$f.Z@}4G(u8MkbIdFwUpJ~u9(nd%lu8MkbIdFwUaZO,H*K2`Ee8MkbIdFwU[D3v'9q~2B*9MkbIdFwUaZO,H*K2`E*9MkbIdFwU%?O,H~_2`E*9MkbIdFwUg+O,H9h2`E*9MkbIdFwUc,O,Hog2`E*9MkbIdFwU_-O,HJg2`E*9MkbIdFwUZ.O,H}f2`E*9MkbIdFwUV0O,HWf2`E*9MkbIdFwUR1O,H.f2`E*9MkbIdFwUN2O,Hee2`E*9MkbIdFwU(g70I8-kkV*9MkbIdFwUGW.0I-5tkV*9MkbIdFwU}5y.ItF+lV*9MkbIdFwU@&amp;q.IjM5lV*9MkbIdFwUl?O.Ihn^lV*9MkbIdFwUWBy.I)C+lV*9MkbIdFwUaY`v'f'P2B*9MkbIdFwUJcTv'MW[2B*9MkbIdFwU6kSv'L3_2B*9MkbIdFwUy.hv'^[G2B*9MkbIdFwU&amp;Wsv'pU72B*9MkbIdFwU7Otv'7g62B*9MkbIdFwUKGuv']w52B*9MkbIdFwU?Iav'oBO2B*9MkbIdFwU$RUv'VnZ2B*9MkbIdFwU5JVv'x!Z2B*9MkbIdFwUIBWv'C5Y2B*9MkbIdFwU8y(w'HF$2B*9MkbIdFwUxp%0Ij`~kV*9MkbIdFwUr7Bv'UEr2B*9MkbIdFwU@]qDYt,uK7W@xTK}UAZQaoe[s)b9Z7%3izG4qOc3wf@_%sbe2Au(qh3f62HtpO'DMliL@9C'V[VqeV?fJ[7'H?Q~PAYa$-TR,SwJ.u*T9l]z`4(PYqFPCrIey6?qsgmA^58hny0Bbb29nSr?]`o7k6Rz'?Wxzihbgp2F[)xX44zq]TpEA47ktWf_!Nz6978].Jy-?0[E</RegistryValue>
  </Registry>
  <Registry>
    <RegistryHive>HKLM:\SOFTWARE\MICROSOFT\WINDOWS\CURRENTVERSION\INSTALLER\USERDATA\S-1-5-18\PRODUCTS\008BB29E5CCB52C41820CAC2B3C7C7E1\INSTALLPROPERTIES</RegistryHive>
    <RegistryDeleteParent>False</RegistryDeleteParent>
    <RegistryType>String</RegistryType>
    <RegistryName>LocalPackage</RegistryName>
    <RegistryValue>C:\WINDOWS\Installer\f82da5.msi</RegistryValue>
  </Registry>
  <Registry>
    <RegistryHive>HKLM:\SOFTWARE\MICROSOFT\WINDOWS\CURRENTVERSION\INSTALLER\USERDATA\S-1-5-18\PRODUCTS\008BB29E5CCB52C41820CAC2B3C7C7E1\INSTALLPROPERTIES</RegistryHive>
    <RegistryDeleteParent>False</RegistryDeleteParent>
    <RegistryType>String</RegistryType>
    <RegistryName>AuthorizedCDFPrefix</RegistryName>
    <RegistryValue>
    </RegistryValue>
  </Registry>
  <Registry>
    <RegistryHive>HKLM:\SOFTWARE\MICROSOFT\WINDOWS\CURRENTVERSION\INSTALLER\USERDATA\S-1-5-18\PRODUCTS\008BB29E5CCB52C41820CAC2B3C7C7E1\INSTALLPROPERTIES</RegistryHive>
    <RegistryDeleteParent>False</RegistryDeleteParent>
    <RegistryType>String</RegistryType>
    <RegistryName>Comments</RegistryName>
    <RegistryValue>
    </RegistryValue>
  </Registry>
  <Registry>
    <RegistryHive>HKLM:\SOFTWARE\MICROSOFT\WINDOWS\CURRENTVERSION\INSTALLER\USERDATA\S-1-5-18\PRODUCTS\008BB29E5CCB52C41820CAC2B3C7C7E1\INSTALLPROPERTIES</RegistryHive>
    <RegistryDeleteParent>False</RegistryDeleteParent>
    <RegistryType>String</RegistryType>
    <RegistryName>Contact</RegistryName>
    <RegistryValue>Assistance AppleCare</RegistryValue>
  </Registry>
  <Registry>
    <RegistryHive>HKLM:\SOFTWARE\MICROSOFT\WINDOWS\CURRENTVERSION\INSTALLER\USERDATA\S-1-5-18\PRODUCTS\008BB29E5CCB52C41820CAC2B3C7C7E1\INSTALLPROPERTIES</RegistryHive>
    <RegistryDeleteParent>False</RegistryDeleteParent>
    <RegistryType>String</RegistryType>
    <RegistryName>DisplayVersion</RegistryName>
    <RegistryValue>5.5</RegistryValue>
  </Registry>
  <Registry>
    <RegistryHive>HKLM:\SOFTWARE\MICROSOFT\WINDOWS\CURRENTVERSION\INSTALLER\USERDATA\S-1-5-18\PRODUCTS\008BB29E5CCB52C41820CAC2B3C7C7E1\INSTALLPROPERTIES</RegistryHive>
    <RegistryDeleteParent>False</RegistryDeleteParent>
    <RegistryType>ExpandString</RegistryType>
    <RegistryName>HelpLink</RegistryName>
    <RegistryValue>http://www.apple.com/fr/support/</RegistryValue>
  </Registry>
  <Registry>
    <RegistryHive>HKLM:\SOFTWARE\MICROSOFT\WINDOWS\CURRENTVERSION\INSTALLER\USERDATA\S-1-5-18\PRODUCTS\008BB29E5CCB52C41820CAC2B3C7C7E1\INSTALLPROPERTIES</RegistryHive>
    <RegistryDeleteParent>False</RegistryDeleteParent>
    <RegistryType>String</RegistryType>
    <RegistryName>HelpTelephone</RegistryName>
    <RegistryValue>0825 888 024</RegistryValue>
  </Registry>
  <Registry>
    <RegistryHive>HKLM:\SOFTWARE\MICROSOFT\WINDOWS\CURRENTVERSION\INSTALLER\USERDATA\S-1-5-18\PRODUCTS\008BB29E5CCB52C41820CAC2B3C7C7E1\INSTALLPROPERTIES</RegistryHive>
    <RegistryDeleteParent>False</RegistryDeleteParent>
    <RegistryType>String</RegistryType>
    <RegistryName>InstallDate</RegistryName>
    <RegistryValue>20170704</RegistryValue>
  </Registry>
  <Registry>
    <RegistryHive>HKLM:\SOFTWARE\MICROSOFT\WINDOWS\CURRENTVERSION\INSTALLER\USERDATA\S-1-5-18\PRODUCTS\008BB29E5CCB52C41820CAC2B3C7C7E1\INSTALLPROPERTIES</RegistryHive>
    <RegistryDeleteParent>False</RegistryDeleteParent>
    <RegistryType>String</RegistryType>
    <RegistryName>InstallLocation</RegistryName>
    <RegistryValue>C:\Program Files (x86)\Common Files\Apple\Apple Application Support\</RegistryValue>
  </Registry>
  <Registry>
    <RegistryHive>HKLM:\SOFTWARE\MICROSOFT\WINDOWS\CURRENTVERSION\INSTALLER\USERDATA\S-1-5-18\PRODUCTS\008BB29E5CCB52C41820CAC2B3C7C7E1\INSTALLPROPERTIES</RegistryHive>
    <RegistryDeleteParent>False</RegistryDeleteParent>
    <RegistryType>String</RegistryType>
    <RegistryName>InstallSource</RegistryName>
    <RegistryValue>C:\Users\Admin\AppData\Local\Temp\IXP776.TMP\</RegistryValue>
  </Registry>
  <Registry>
    <RegistryHive>HKLM:\SOFTWARE\MICROSOFT\WINDOWS\CURRENTVERSION\INSTALLER\USERDATA\S-1-5-18\PRODUCTS\008BB29E5CCB52C41820CAC2B3C7C7E1\INSTALLPROPERTIES</RegistryHive>
    <RegistryDeleteParent>False</RegistryDeleteParent>
    <RegistryType>ExpandString</RegistryType>
    <RegistryName>ModifyPath</RegistryName>
    <RegistryValue>MsiExec.exe /I{E92BB800-BCC5-4C25-8102-AC2C3B7C7C1E}</RegistryValue>
  </Registry>
  <Registry>
    <RegistryHive>HKLM:\SOFTWARE\MICROSOFT\WINDOWS\CURRENTVERSION\INSTALLER\USERDATA\S-1-5-18\PRODUCTS\008BB29E5CCB52C41820CAC2B3C7C7E1\INSTALLPROPERTIES</RegistryHive>
    <RegistryDeleteParent>False</RegistryDeleteParent>
    <RegistryType>String</RegistryType>
    <RegistryName>Publisher</RegistryName>
    <RegistryValue>Apple Inc.</RegistryValue>
  </Registry>
  <Registry>
    <RegistryHive>HKLM:\SOFTWARE\MICROSOFT\WINDOWS\CURRENTVERSION\INSTALLER\USERDATA\S-1-5-18\PRODUCTS\008BB29E5CCB52C41820CAC2B3C7C7E1\INSTALLPROPERTIES</RegistryHive>
    <RegistryDeleteParent>False</RegistryDeleteParent>
    <RegistryType>String</RegistryType>
    <RegistryName>Readme</RegistryName>
    <RegistryValue>
    </RegistryValue>
  </Registry>
  <Registry>
    <RegistryHive>HKLM:\SOFTWARE\MICROSOFT\WINDOWS\CURRENTVERSION\INSTALLER\USERDATA\S-1-5-18\PRODUCTS\008BB29E5CCB52C41820CAC2B3C7C7E1\INSTALLPROPERTIES</RegistryHive>
    <RegistryDeleteParent>False</RegistryDeleteParent>
    <RegistryType>String</RegistryType>
    <RegistryName>Size</RegistryName>
    <RegistryValue>
    </RegistryValue>
  </Registry>
  <Registry>
    <RegistryHive>HKLM:\SOFTWARE\MICROSOFT\WINDOWS\CURRENTVERSION\INSTALLER\USERDATA\S-1-5-18\PRODUCTS\008BB29E5CCB52C41820CAC2B3C7C7E1\INSTALLPROPERTIES</RegistryHive>
    <RegistryDeleteParent>False</RegistryDeleteParent>
    <RegistryType>DWord</RegistryType>
    <RegistryName>EstimatedSize</RegistryName>
    <RegistryValue>1fca3</RegistryValue>
  </Registry>
  <Registry>
    <RegistryHive>HKLM:\SOFTWARE\MICROSOFT\WINDOWS\CURRENTVERSION\INSTALLER\USERDATA\S-1-5-18\PRODUCTS\008BB29E5CCB52C41820CAC2B3C7C7E1\INSTALLPROPERTIES</RegistryHive>
    <RegistryDeleteParent>False</RegistryDeleteParent>
    <RegistryType>ExpandString</RegistryType>
    <RegistryName>UninstallString</RegistryName>
    <RegistryValue>MsiExec.exe /I{E92BB800-BCC5-4C25-8102-AC2C3B7C7C1E}</RegistryValue>
  </Registry>
  <Registry>
    <RegistryHive>HKLM:\SOFTWARE\MICROSOFT\WINDOWS\CURRENTVERSION\INSTALLER\USERDATA\S-1-5-18\PRODUCTS\008BB29E5CCB52C41820CAC2B3C7C7E1\INSTALLPROPERTIES</RegistryHive>
    <RegistryDeleteParent>False</RegistryDeleteParent>
    <RegistryType>String</RegistryType>
    <RegistryName>URLInfoAbout</RegistryName>
    <RegistryValue>http://www.apple.com/fr</RegistryValue>
  </Registry>
  <Registry>
    <RegistryHive>HKLM:\SOFTWARE\MICROSOFT\WINDOWS\CURRENTVERSION\INSTALLER\USERDATA\S-1-5-18\PRODUCTS\008BB29E5CCB52C41820CAC2B3C7C7E1\INSTALLPROPERTIES</RegistryHive>
    <RegistryDeleteParent>False</RegistryDeleteParent>
    <RegistryType>String</RegistryType>
    <RegistryName>URLUpdateInfo</RegistryName>
    <RegistryValue>http://www.apple.com/fr</RegistryValue>
  </Registry>
  <Registry>
    <RegistryHive>HKLM:\SOFTWARE\MICROSOFT\WINDOWS\CURRENTVERSION\INSTALLER\USERDATA\S-1-5-18\PRODUCTS\008BB29E5CCB52C41820CAC2B3C7C7E1\INSTALLPROPERTIES</RegistryHive>
    <RegistryDeleteParent>False</RegistryDeleteParent>
    <RegistryType>DWord</RegistryType>
    <RegistryName>VersionMajor</RegistryName>
    <RegistryValue>5</RegistryValue>
  </Registry>
  <Registry>
    <RegistryHive>HKLM:\SOFTWARE\MICROSOFT\WINDOWS\CURRENTVERSION\INSTALLER\USERDATA\S-1-5-18\PRODUCTS\008BB29E5CCB52C41820CAC2B3C7C7E1\INSTALLPROPERTIES</RegistryHive>
    <RegistryDeleteParent>False</RegistryDeleteParent>
    <RegistryType>DWord</RegistryType>
    <RegistryName>VersionMinor</RegistryName>
    <RegistryValue>5</RegistryValue>
  </Registry>
  <Registry>
    <RegistryHive>HKLM:\SOFTWARE\MICROSOFT\WINDOWS\CURRENTVERSION\INSTALLER\USERDATA\S-1-5-18\PRODUCTS\008BB29E5CCB52C41820CAC2B3C7C7E1\INSTALLPROPERTIES</RegistryHive>
    <RegistryDeleteParent>False</RegistryDeleteParent>
    <RegistryType>DWord</RegistryType>
    <RegistryName>WindowsInstaller</RegistryName>
    <RegistryValue>1</RegistryValue>
  </Registry>
  <Registry>
    <RegistryHive>HKLM:\SOFTWARE\MICROSOFT\WINDOWS\CURRENTVERSION\INSTALLER\USERDATA\S-1-5-18\PRODUCTS\008BB29E5CCB52C41820CAC2B3C7C7E1\INSTALLPROPERTIES</RegistryHive>
    <RegistryDeleteParent>False</RegistryDeleteParent>
    <RegistryType>DWord</RegistryType>
    <RegistryName>Version</RegistryName>
    <RegistryValue>5050000</RegistryValue>
  </Registry>
  <Registry>
    <RegistryHive>HKLM:\SOFTWARE\MICROSOFT\WINDOWS\CURRENTVERSION\INSTALLER\USERDATA\S-1-5-18\PRODUCTS\008BB29E5CCB52C41820CAC2B3C7C7E1\INSTALLPROPERTIES</RegistryHive>
    <RegistryDeleteParent>False</RegistryDeleteParent>
    <RegistryType>DWord</RegistryType>
    <RegistryName>Language</RegistryName>
    <RegistryValue>40c</RegistryValue>
  </Registry>
  <Registry>
    <RegistryHive>HKLM:\SOFTWARE\MICROSOFT\WINDOWS\CURRENTVERSION\INSTALLER\USERDATA\S-1-5-18\PRODUCTS\008BB29E5CCB52C41820CAC2B3C7C7E1\INSTALLPROPERTIES</RegistryHive>
    <RegistryDeleteParent>False</RegistryDeleteParent>
    <RegistryType>String</RegistryType>
    <RegistryName>DisplayName</RegistryName>
    <RegistryValue>Apple Application Support (32 bits)</RegistryValue>
  </Registry>
  <Registry>
    <RegistryHive>HKLM:\SOFTWARE\MICROSOFT\WINDOWS\CURRENTVERSION\INSTALLER\USERDATA\S-1-5-18\PRODUCTS\008BB29E5CCB52C41820CAC2B3C7C7E1\PATCHES</RegistryHive>
    <RegistryDeleteParent>False</RegistryDeleteParent>
    <RegistryType>String</RegistryType>
    <RegistryName>AllPatches</RegistryName>
    <RegistryValue>
    </RegistryValue>
  </Registry>
  <Registry>
    <RegistryHive>HKCR:\Installer\Products\008BB29E5CCB52C41820CAC2B3C7C7E1</RegistryHive>
    <RegistryDeleteParent>False</RegistryDeleteParent>
    <RegistryType>String</RegistryType>
    <RegistryName>ProductName</RegistryName>
    <RegistryValue>Apple Application Support (32 bits)</RegistryValue>
  </Registry>
  <Registry>
    <RegistryHive>HKCR:\Installer\Products\008BB29E5CCB52C41820CAC2B3C7C7E1</RegistryHive>
    <RegistryDeleteParent>False</RegistryDeleteParent>
    <RegistryType>String</RegistryType>
    <RegistryName>PackageCode</RegistryName>
    <RegistryValue>981866E82C5A85B4195F066203151C93</RegistryValue>
  </Registry>
  <Registry>
    <RegistryHive>HKCR:\Installer\Products\008BB29E5CCB52C41820CAC2B3C7C7E1</RegistryHive>
    <RegistryDeleteParent>False</RegistryDeleteParent>
    <RegistryType>DWord</RegistryType>
    <RegistryName>Language</RegistryName>
    <RegistryValue>40c</RegistryValue>
  </Registry>
  <Registry>
    <RegistryHive>HKCR:\Installer\Products\008BB29E5CCB52C41820CAC2B3C7C7E1</RegistryHive>
    <RegistryDeleteParent>False</RegistryDeleteParent>
    <RegistryType>DWord</RegistryType>
    <RegistryName>Version</RegistryName>
    <RegistryValue>5050000</RegistryValue>
  </Registry>
  <Registry>
    <RegistryHive>HKCR:\Installer\Products\008BB29E5CCB52C41820CAC2B3C7C7E1</RegistryHive>
    <RegistryDeleteParent>False</RegistryDeleteParent>
    <RegistryType>DWord</RegistryType>
    <RegistryName>Assignment</RegistryName>
    <RegistryValue>1</RegistryValue>
  </Registry>
  <Registry>
    <RegistryHive>HKCR:\Installer\Products\008BB29E5CCB52C41820CAC2B3C7C7E1</RegistryHive>
    <RegistryDeleteParent>False</RegistryDeleteParent>
    <RegistryType>DWord</RegistryType>
    <RegistryName>AdvertiseFlags</RegistryName>
    <RegistryValue>184</RegistryValue>
  </Registry>
  <Registry>
    <RegistryHive>HKCR:\Installer\Products\008BB29E5CCB52C41820CAC2B3C7C7E1</RegistryHive>
    <RegistryDeleteParent>False</RegistryDeleteParent>
    <RegistryType>String</RegistryType>
    <RegistryName>ProductIcon</RegistryName>
    <RegistryValue>C:\WINDOWS\Installer\{E92BB800-BCC5-4C25-8102-AC2C3B7C7C1E}\WinInstall.ico</RegistryValue>
  </Registry>
  <Registry>
    <RegistryHive>HKCR:\Installer\Products\008BB29E5CCB52C41820CAC2B3C7C7E1</RegistryHive>
    <RegistryDeleteParent>False</RegistryDeleteParent>
    <RegistryType>DWord</RegistryType>
    <RegistryName>InstanceType</RegistryName>
    <RegistryValue>0</RegistryValue>
  </Registry>
  <Registry>
    <RegistryHive>HKCR:\Installer\Products\008BB29E5CCB52C41820CAC2B3C7C7E1</RegistryHive>
    <RegistryDeleteParent>False</RegistryDeleteParent>
    <RegistryType>DWord</RegistryType>
    <RegistryName>AuthorizedLUAApp</RegistryName>
    <RegistryValue>0</RegistryValue>
  </Registry>
  <Registry>
    <RegistryHive>HKCR:\Installer\Products\008BB29E5CCB52C41820CAC2B3C7C7E1</RegistryHive>
    <RegistryDeleteParent>False</RegistryDeleteParent>
    <RegistryType>DWord</RegistryType>
    <RegistryName>DeploymentFlags</RegistryName>
    <RegistryValue>3</RegistryValue>
  </Registry>
  <Registry>
    <RegistryHive>HKCR:\Installer\Products\008BB29E5CCB52C41820CAC2B3C7C7E1</RegistryHive>
    <RegistryDeleteParent>False</RegistryDeleteParent>
    <RegistryType>MultiString</RegistryType>
    <RegistryName>Clients</RegistryName>
    <RegistryValue>:</RegistryValue>
  </Registry>
  <Registry>
    <RegistryHive>HKCR:\INSTALLER\PRODUCTS\008BB29E5CCB52C41820CAC2B3C7C7E1\SOURCELIST</RegistryHive>
    <RegistryDeleteParent>False</RegistryDeleteParent>
    <RegistryType>String</RegistryType>
    <RegistryName>PackageName</RegistryName>
    <RegistryValue>AppleApplicationSupport.msi</RegistryValue>
  </Registry>
  <Registry>
    <RegistryHive>HKCR:\INSTALLER\PRODUCTS\008BB29E5CCB52C41820CAC2B3C7C7E1\SOURCELIST</RegistryHive>
    <RegistryDeleteParent>False</RegistryDeleteParent>
    <RegistryType>ExpandString</RegistryType>
    <RegistryName>LastUsedSource</RegistryName>
    <RegistryValue>n;7;C:\Users\Admin\AppData\Local\Temp\IXP351.TMP\</RegistryValue>
  </Registry>
  <Registry>
    <RegistryHive>HKCR:\INSTALLER\PRODUCTS\008BB29E5CCB52C41820CAC2B3C7C7E1\SOURCELIST\MEDIA</RegistryHive>
    <RegistryDeleteParent>False</RegistryDeleteParent>
    <RegistryType>String</RegistryType>
    <RegistryName>1</RegistryName>
    <RegistryValue>;</RegistryValue>
  </Registry>
  <Registry>
    <RegistryHive>HKCR:\INSTALLER\PRODUCTS\008BB29E5CCB52C41820CAC2B3C7C7E1\SOURCELIST\NET</RegistryHive>
    <RegistryDeleteParent>False</RegistryDeleteParent>
    <RegistryType>ExpandString</RegistryType>
    <RegistryName>1</RegistryName>
    <RegistryValue>C:\Users\Admin\AppData\Local\Temp\IXP776.TMP\</RegistryValue>
  </Registry>
  <Registry>
    <RegistryHive>HKCR:\INSTALLER\PRODUCTS\008BB29E5CCB52C41820CAC2B3C7C7E1\SOURCELIST\NET</RegistryHive>
    <RegistryDeleteParent>False</RegistryDeleteParent>
    <RegistryType>ExpandString</RegistryType>
    <RegistryName>2</RegistryName>
    <RegistryValue>C:\ProgramData\Apple\Installer Cache\AppleApplicationSupport 5.5\</RegistryValue>
  </Registry>
  <Registry>
    <RegistryHive>HKCR:\INSTALLER\PRODUCTS\008BB29E5CCB52C41820CAC2B3C7C7E1\SOURCELIST\NET</RegistryHive>
    <RegistryDeleteParent>False</RegistryDeleteParent>
    <RegistryType>ExpandString</RegistryType>
    <RegistryName>3</RegistryName>
    <RegistryValue>C:\Users\Admin\AppData\Local\Temp\IXP502.TMP\</RegistryValue>
  </Registry>
  <Registry>
    <RegistryHive>HKCR:\INSTALLER\PRODUCTS\008BB29E5CCB52C41820CAC2B3C7C7E1\SOURCELIST\NET</RegistryHive>
    <RegistryDeleteParent>False</RegistryDeleteParent>
    <RegistryType>ExpandString</RegistryType>
    <RegistryName>4</RegistryName>
    <RegistryValue>C:\Users\Admin\AppData\Local\Temp\IXP943.TMP\</RegistryValue>
  </Registry>
  <Registry>
    <RegistryHive>HKCR:\INSTALLER\PRODUCTS\008BB29E5CCB52C41820CAC2B3C7C7E1\SOURCELIST\NET</RegistryHive>
    <RegistryDeleteParent>False</RegistryDeleteParent>
    <RegistryType>ExpandString</RegistryType>
    <RegistryName>5</RegistryName>
    <RegistryValue>C:\Users\Admin\AppData\Local\Temp\IXP856.TMP\</RegistryValue>
  </Registry>
  <Registry>
    <RegistryHive>HKCR:\INSTALLER\PRODUCTS\008BB29E5CCB52C41820CAC2B3C7C7E1\SOURCELIST\NET</RegistryHive>
    <RegistryDeleteParent>False</RegistryDeleteParent>
    <RegistryType>ExpandString</RegistryType>
    <RegistryName>6</RegistryName>
    <RegistryValue>C:\Users\Admin\AppData\Local\Temp\IXP736.TMP\</RegistryValue>
  </Registry>
  <Registry>
    <RegistryHive>HKCR:\INSTALLER\PRODUCTS\008BB29E5CCB52C41820CAC2B3C7C7E1\SOURCELIST\NET</RegistryHive>
    <RegistryDeleteParent>False</RegistryDeleteParent>
    <RegistryType>ExpandString</RegistryType>
    <RegistryName>7</RegistryName>
    <RegistryValue>C:\Users\Admin\AppData\Local\Temp\IXP351.TMP\</RegistryValue>
  </Registry>
</RegistryBackup>